{"link_name": "epson_WF-C57xx", "type": "Template", "OS": "", "vendor": "Others", "minZabbVer": "5.0.x", "link_desc": "<p>Collect ink level data by SNMP and/or web. Tested on Epson WF-C5790 (color) and WF-C5799 (black).</p>", "features": "SNMP Agent", "address": "", "city": "", "state": "", "country": "", "postcode": "", "telephone": "", "fax": "", "email": "", "website": "https://github.com/skvsbk/zabbix_template/tree/main/epson_57xx", "price": 0, "link_hits": 498, "link_votes": null, "link_rating": 0, "link_featured": null, "link_created": "2021-03-29 10:18:29", "link_modified": "2021-03-29 10:20:19", "link_visited": 223, "publish_up": "2021-03-29 10:18:29", "publish_down": "0000-00-00 00:00:00", "metakey": "", "metadesc": "", "1.8": "", "2.0": "", "2.2": "", "2.4": "", "3.0": "", "3.2": "", "3.4": "", "4.0": "", "4.2": "", "4.4": "", "5.0": "", "5.2": "", "tags": "", "author": "Konstantin Svitochev", "user_id": 13203, "link_id": 2394, "cat_id": "109", "internal_notes": "", "lat": 0, "lng": 0, "zoom": ""}