{"link_name": "LM-Sensors SNMP", "type": "Template", "OS": "", "vendor": "Others", "minZabbVer": "4.4.x", "link_desc": "<p>For Zabbix 5, an SNMP template for LM-SENSORS mib, used in freenas 11.</p>", "features": "Low Level Discovery (LLD)|SNMP Agent", "address": "", "city": "", "state": "", "country": "", "postcode": "", "telephone": "", "fax": "", "email": "", "website": "https://github.com/garbled1/Zabbix-Templates/blob/master/UCD-SNMP/LM-SENSORS-SNMPv2.xml", "price": 0, "link_hits": 1717, "link_votes": null, "link_rating": 0, "link_featured": null, "link_created": "2020-06-14 21:22:15", "link_modified": "0000-00-00 00:00:00", "link_visited": 626, "publish_up": "2020-06-14 21:22:15", "publish_down": "0000-00-00 00:00:00", "metakey": "", "metadesc": "", "1.8": "", "2.0": "", "2.2": "", "2.4": "", "3.0": "", "3.2": "", "3.4": "", "4.0": "", "4.2": "", "4.4": "", "5.0": "", "5.2": "", "tags": "freenas, lm-sensors, lmsensors", "author": "Tim Rightnour", "user_id": 8973, "link_id": 2122, "cat_id": "114", "internal_notes": "", "lat": 0, "lng": 0, "zoom": ""}