<?xml version="1.0" encoding="UTF-8"?>
<zabbix_export>
    <version>4.2</version>
    <date>2019-05-16T16:21:30Z</date>
    <groups>
        <group>
            <name>Templates/Printers</name>
        </group>
    </groups>
    <templates>
        <template>
            <template>Template Canon IPF Color printers</template>
            <name>Template Canon IPF Color printers</name>
            <description>Template for color Canon IPF Multi Functional printer.</description>
            <groups>
                <group>
                    <name>Templates/Printers</name>
                </group>
            </groups>
            <applications/>
            <items>
                <item>
                    <name>BlackIPF.toner.model</name>
                    <type>1</type>
                    <snmp_community>public</snmp_community>
                    <snmp_oid>.1.3.6.1.2.1.43.11.1.1.6.1.6</snmp_oid>
                    <key>BlackIPF.toner.model</key>
                    <delay>6h</delay>
                    <history>7d</history>
                    <trends>0</trends>
                    <status>0</status>
                    <value_type>1</value_type>
                    <allowed_hosts/>
                    <units/>
                    <snmpv3_contextname/>
                    <snmpv3_securityname/>
                    <snmpv3_securitylevel>0</snmpv3_securitylevel>
                    <snmpv3_authprotocol>0</snmpv3_authprotocol>
                    <snmpv3_authpassphrase/>
                    <snmpv3_privprotocol>0</snmpv3_privprotocol>
                    <snmpv3_privpassphrase/>
                    <params/>
                    <ipmi_sensor/>
                    <authtype>0</authtype>
                    <username/>
                    <password/>
                    <publickey/>
                    <privatekey/>
                    <port>161</port>
                    <description>Shows printer toner model and name.&#13;
BlackInkCartridge</description>
                    <inventory_link>0</inventory_link>
                    <applications/>
                    <valuemap/>
                    <logtimefmt/>
                    <preprocessing/>
                    <jmx_endpoint/>
                    <timeout>3s</timeout>
                    <url/>
                    <query_fields/>
                    <posts/>
                    <status_codes>200</status_codes>
                    <follow_redirects>1</follow_redirects>
                    <post_type>0</post_type>
                    <http_proxy/>
                    <headers/>
                    <retrieve_mode>0</retrieve_mode>
                    <request_method>0</request_method>
                    <output_format>0</output_format>
                    <allow_traps>0</allow_traps>
                    <ssl_cert_file/>
                    <ssl_key_file/>
                    <ssl_key_password/>
                    <verify_peer>0</verify_peer>
                    <verify_host>0</verify_host>
                    <master_item/>
                </item>
                <item>
                    <name>Canon.model</name>
                    <type>1</type>
                    <snmp_community>public</snmp_community>
                    <snmp_oid>.1.3.6.1.2.1.1.1.0</snmp_oid>
                    <key>Canon.model</key>
                    <delay>6h</delay>
                    <history>7d</history>
                    <trends>0</trends>
                    <status>0</status>
                    <value_type>4</value_type>
                    <allowed_hosts/>
                    <units/>
                    <snmpv3_contextname/>
                    <snmpv3_securityname/>
                    <snmpv3_securitylevel>0</snmpv3_securitylevel>
                    <snmpv3_authprotocol>0</snmpv3_authprotocol>
                    <snmpv3_authpassphrase/>
                    <snmpv3_privprotocol>0</snmpv3_privprotocol>
                    <snmpv3_privpassphrase/>
                    <params/>
                    <ipmi_sensor/>
                    <authtype>0</authtype>
                    <username/>
                    <password/>
                    <publickey/>
                    <privatekey/>
                    <port/>
                    <description>Printer model.</description>
                    <inventory_link>0</inventory_link>
                    <applications/>
                    <valuemap/>
                    <logtimefmt/>
                    <preprocessing/>
                    <jmx_endpoint/>
                    <timeout>3s</timeout>
                    <url/>
                    <query_fields/>
                    <posts/>
                    <status_codes>200</status_codes>
                    <follow_redirects>1</follow_redirects>
                    <post_type>0</post_type>
                    <http_proxy/>
                    <headers/>
                    <retrieve_mode>0</retrieve_mode>
                    <request_method>0</request_method>
                    <output_format>0</output_format>
                    <allow_traps>0</allow_traps>
                    <ssl_cert_file/>
                    <ssl_key_file/>
                    <ssl_key_password/>
                    <verify_peer>0</verify_peer>
                    <verify_host>0</verify_host>
                    <master_item/>
                </item>
                <item>
                    <name>CyanIPF.toner.model</name>
                    <type>1</type>
                    <snmp_community>public</snmp_community>
                    <snmp_oid>.1.3.6.1.2.1.43.11.1.1.6.1.1</snmp_oid>
                    <key>CyanIPF.toner.model</key>
                    <delay>6h</delay>
                    <history>30d</history>
                    <trends>0</trends>
                    <status>0</status>
                    <value_type>1</value_type>
                    <allowed_hosts/>
                    <units/>
                    <snmpv3_contextname/>
                    <snmpv3_securityname/>
                    <snmpv3_securitylevel>0</snmpv3_securitylevel>
                    <snmpv3_authprotocol>0</snmpv3_authprotocol>
                    <snmpv3_authpassphrase/>
                    <snmpv3_privprotocol>0</snmpv3_privprotocol>
                    <snmpv3_privpassphrase/>
                    <params/>
                    <ipmi_sensor/>
                    <authtype>0</authtype>
                    <username/>
                    <password/>
                    <publickey/>
                    <privatekey/>
                    <port/>
                    <description>Shows black toner name and model.&#13;
CyanInkCartridge</description>
                    <inventory_link>0</inventory_link>
                    <applications/>
                    <valuemap/>
                    <logtimefmt/>
                    <preprocessing/>
                    <jmx_endpoint/>
                    <timeout>3s</timeout>
                    <url/>
                    <query_fields/>
                    <posts/>
                    <status_codes>200</status_codes>
                    <follow_redirects>1</follow_redirects>
                    <post_type>0</post_type>
                    <http_proxy/>
                    <headers/>
                    <retrieve_mode>0</retrieve_mode>
                    <request_method>0</request_method>
                    <output_format>0</output_format>
                    <allow_traps>0</allow_traps>
                    <ssl_cert_file/>
                    <ssl_key_file/>
                    <ssl_key_password/>
                    <verify_peer>0</verify_peer>
                    <verify_host>0</verify_host>
                    <master_item/>
                </item>
                <item>
                    <name>Device.IP.address</name>
                    <type>1</type>
                    <snmp_community>public</snmp_community>
                    <snmp_oid>.1.3.6.1.4.1.1602.1.3.3.1.11.1.1.2.1</snmp_oid>
                    <key>Device.IP.address</key>
                    <delay>6h</delay>
                    <history>7d</history>
                    <trends>0</trends>
                    <status>0</status>
                    <value_type>4</value_type>
                    <allowed_hosts/>
                    <units/>
                    <snmpv3_contextname/>
                    <snmpv3_securityname/>
                    <snmpv3_securitylevel>0</snmpv3_securitylevel>
                    <snmpv3_authprotocol>0</snmpv3_authprotocol>
                    <snmpv3_authpassphrase/>
                    <snmpv3_privprotocol>0</snmpv3_privprotocol>
                    <snmpv3_privpassphrase/>
                    <params/>
                    <ipmi_sensor/>
                    <authtype>0</authtype>
                    <username/>
                    <password/>
                    <publickey/>
                    <privatekey/>
                    <port/>
                    <description>Shows device IP address</description>
                    <inventory_link>0</inventory_link>
                    <applications/>
                    <valuemap/>
                    <logtimefmt/>
                    <preprocessing/>
                    <jmx_endpoint/>
                    <timeout>3s</timeout>
                    <url/>
                    <query_fields/>
                    <posts/>
                    <status_codes>200</status_codes>
                    <follow_redirects>1</follow_redirects>
                    <post_type>0</post_type>
                    <http_proxy/>
                    <headers/>
                    <retrieve_mode>0</retrieve_mode>
                    <request_method>0</request_method>
                    <output_format>0</output_format>
                    <allow_traps>0</allow_traps>
                    <ssl_cert_file/>
                    <ssl_key_file/>
                    <ssl_key_password/>
                    <verify_peer>0</verify_peer>
                    <verify_host>0</verify_host>
                    <master_item/>
                </item>
                <item>
                    <name>Device.SN</name>
                    <type>1</type>
                    <snmp_community>public</snmp_community>
                    <snmp_oid>.1.3.6.1.4.1.1602.1.2.1.8.1.3.1.1</snmp_oid>
                    <key>Device.SN</key>
                    <delay>6h</delay>
                    <history>90d</history>
                    <trends>0</trends>
                    <status>0</status>
                    <value_type>4</value_type>
                    <allowed_hosts/>
                    <units/>
                    <snmpv3_contextname/>
                    <snmpv3_securityname/>
                    <snmpv3_securitylevel>0</snmpv3_securitylevel>
                    <snmpv3_authprotocol>0</snmpv3_authprotocol>
                    <snmpv3_authpassphrase/>
                    <snmpv3_privprotocol>0</snmpv3_privprotocol>
                    <snmpv3_privpassphrase/>
                    <params/>
                    <ipmi_sensor/>
                    <authtype>0</authtype>
                    <username/>
                    <password/>
                    <publickey/>
                    <privatekey/>
                    <port/>
                    <description/>
                    <inventory_link>0</inventory_link>
                    <applications>
                        <application>
                            <name>Status</name>
                        </application>
                    </applications>
                    <valuemap/>
                    <logtimefmt/>
                    <preprocessing/>
                    <jmx_endpoint/>
                    <timeout>3s</timeout>
                    <url/>
                    <query_fields/>
                    <posts/>
                    <status_codes>200</status_codes>
                    <follow_redirects>1</follow_redirects>
                    <post_type>0</post_type>
                    <http_proxy/>
                    <headers/>
                    <retrieve_mode>0</retrieve_mode>
                    <request_method>0</request_method>
                    <output_format>0</output_format>
                    <allow_traps>0</allow_traps>
                    <ssl_cert_file/>
                    <ssl_key_file/>
                    <ssl_key_password/>
                    <verify_peer>0</verify_peer>
                    <verify_host>0</verify_host>
                    <master_item/>
                </item>
                <item>
                    <name>MagentaIPF.toner.model</name>
                    <type>1</type>
                    <snmp_community>public</snmp_community>
                    <snmp_oid>.1.3.6.1.2.1.43.11.1.1.6.1.2</snmp_oid>
                    <key>MagentaIPF.toner.model</key>
                    <delay>6h</delay>
                    <history>7d</history>
                    <trends>0</trends>
                    <status>0</status>
                    <value_type>1</value_type>
                    <allowed_hosts/>
                    <units/>
                    <snmpv3_contextname/>
                    <snmpv3_securityname/>
                    <snmpv3_securitylevel>0</snmpv3_securitylevel>
                    <snmpv3_authprotocol>0</snmpv3_authprotocol>
                    <snmpv3_authpassphrase/>
                    <snmpv3_privprotocol>0</snmpv3_privprotocol>
                    <snmpv3_privpassphrase/>
                    <params/>
                    <ipmi_sensor/>
                    <authtype>0</authtype>
                    <username/>
                    <password/>
                    <publickey/>
                    <privatekey/>
                    <port>161</port>
                    <description>Shows printer cyan toner model and name.&#13;
MagentaInkCartridge</description>
                    <inventory_link>0</inventory_link>
                    <applications/>
                    <valuemap/>
                    <logtimefmt/>
                    <preprocessing/>
                    <jmx_endpoint/>
                    <timeout>3s</timeout>
                    <url/>
                    <query_fields/>
                    <posts/>
                    <status_codes>200</status_codes>
                    <follow_redirects>1</follow_redirects>
                    <post_type>0</post_type>
                    <http_proxy/>
                    <headers/>
                    <retrieve_mode>0</retrieve_mode>
                    <request_method>0</request_method>
                    <output_format>0</output_format>
                    <allow_traps>0</allow_traps>
                    <ssl_cert_file/>
                    <ssl_key_file/>
                    <ssl_key_password/>
                    <verify_peer>0</verify_peer>
                    <verify_host>0</verify_host>
                    <master_item/>
                </item>
                <item>
                    <name>MattBlackIPF1.toner.model</name>
                    <type>1</type>
                    <snmp_community>public</snmp_community>
                    <snmp_oid>.1.3.6.1.2.1.43.11.1.1.6.1.4</snmp_oid>
                    <key>MattBlackIPF1.toner.model</key>
                    <delay>6h</delay>
                    <history>7d</history>
                    <trends>0</trends>
                    <status>0</status>
                    <value_type>1</value_type>
                    <allowed_hosts/>
                    <units/>
                    <snmpv3_contextname/>
                    <snmpv3_securityname/>
                    <snmpv3_securitylevel>0</snmpv3_securitylevel>
                    <snmpv3_authprotocol>0</snmpv3_authprotocol>
                    <snmpv3_authpassphrase/>
                    <snmpv3_privprotocol>0</snmpv3_privprotocol>
                    <snmpv3_privpassphrase/>
                    <params/>
                    <ipmi_sensor/>
                    <authtype>0</authtype>
                    <username/>
                    <password/>
                    <publickey/>
                    <privatekey/>
                    <port>161</port>
                    <description>Shows printer toner model and name.&#13;
MattBlackInkCartridge</description>
                    <inventory_link>0</inventory_link>
                    <applications/>
                    <valuemap/>
                    <logtimefmt/>
                    <preprocessing/>
                    <jmx_endpoint/>
                    <timeout>3s</timeout>
                    <url/>
                    <query_fields/>
                    <posts/>
                    <status_codes>200</status_codes>
                    <follow_redirects>1</follow_redirects>
                    <post_type>0</post_type>
                    <http_proxy/>
                    <headers/>
                    <retrieve_mode>0</retrieve_mode>
                    <request_method>0</request_method>
                    <output_format>0</output_format>
                    <allow_traps>0</allow_traps>
                    <ssl_cert_file/>
                    <ssl_key_file/>
                    <ssl_key_password/>
                    <verify_peer>0</verify_peer>
                    <verify_host>0</verify_host>
                    <master_item/>
                </item>
                <item>
                    <name>MattBlackIPF2.toner.model</name>
                    <type>1</type>
                    <snmp_community>public</snmp_community>
                    <snmp_oid>.1.3.6.1.2.1.43.11.1.1.6.1.5</snmp_oid>
                    <key>MattBlackIPF2.toner.model</key>
                    <delay>6h</delay>
                    <history>7d</history>
                    <trends>0</trends>
                    <status>0</status>
                    <value_type>1</value_type>
                    <allowed_hosts/>
                    <units/>
                    <snmpv3_contextname/>
                    <snmpv3_securityname/>
                    <snmpv3_securitylevel>0</snmpv3_securitylevel>
                    <snmpv3_authprotocol>0</snmpv3_authprotocol>
                    <snmpv3_authpassphrase/>
                    <snmpv3_privprotocol>0</snmpv3_privprotocol>
                    <snmpv3_privpassphrase/>
                    <params/>
                    <ipmi_sensor/>
                    <authtype>0</authtype>
                    <username/>
                    <password/>
                    <publickey/>
                    <privatekey/>
                    <port>161</port>
                    <description>Shows printer toner model and name.&#13;
MattBlackInkCartridge</description>
                    <inventory_link>0</inventory_link>
                    <applications/>
                    <valuemap/>
                    <logtimefmt/>
                    <preprocessing/>
                    <jmx_endpoint/>
                    <timeout>3s</timeout>
                    <url/>
                    <query_fields/>
                    <posts/>
                    <status_codes>200</status_codes>
                    <follow_redirects>1</follow_redirects>
                    <post_type>0</post_type>
                    <http_proxy/>
                    <headers/>
                    <retrieve_mode>0</retrieve_mode>
                    <request_method>0</request_method>
                    <output_format>0</output_format>
                    <allow_traps>0</allow_traps>
                    <ssl_cert_file/>
                    <ssl_key_file/>
                    <ssl_key_password/>
                    <verify_peer>0</verify_peer>
                    <verify_host>0</verify_host>
                    <master_item/>
                </item>
                <item>
                    <name>Toner.Black.level.max</name>
                    <type>1</type>
                    <snmp_community>public</snmp_community>
                    <snmp_oid>.1.3.6.1.2.1.43.11.1.1.8.1.6</snmp_oid>
                    <key>Toner.Black.level.max</key>
                    <delay>3h</delay>
                    <history>7d</history>
                    <trends>30d</trends>
                    <status>0</status>
                    <value_type>0</value_type>
                    <allowed_hosts/>
                    <units/>
                    <snmpv3_contextname/>
                    <snmpv3_securityname/>
                    <snmpv3_securitylevel>0</snmpv3_securitylevel>
                    <snmpv3_authprotocol>0</snmpv3_authprotocol>
                    <snmpv3_authpassphrase/>
                    <snmpv3_privprotocol>0</snmpv3_privprotocol>
                    <snmpv3_privpassphrase/>
                    <params/>
                    <ipmi_sensor/>
                    <authtype>0</authtype>
                    <username/>
                    <password/>
                    <publickey/>
                    <privatekey/>
                    <port>161</port>
                    <description>Max Nuber of Black toner.</description>
                    <inventory_link>0</inventory_link>
                    <applications/>
                    <valuemap/>
                    <logtimefmt/>
                    <preprocessing/>
                    <jmx_endpoint/>
                    <timeout>3s</timeout>
                    <url/>
                    <query_fields/>
                    <posts/>
                    <status_codes>200</status_codes>
                    <follow_redirects>1</follow_redirects>
                    <post_type>0</post_type>
                    <http_proxy/>
                    <headers/>
                    <retrieve_mode>0</retrieve_mode>
                    <request_method>0</request_method>
                    <output_format>0</output_format>
                    <allow_traps>0</allow_traps>
                    <ssl_cert_file/>
                    <ssl_key_file/>
                    <ssl_key_password/>
                    <verify_peer>0</verify_peer>
                    <verify_host>0</verify_host>
                    <master_item/>
                </item>
                <item>
                    <name>Toner.Black.level.now</name>
                    <type>1</type>
                    <snmp_community>public</snmp_community>
                    <snmp_oid>.1.3.6.1.2.1.43.11.1.1.9.1.6</snmp_oid>
                    <key>Toner.Black.level.now</key>
                    <delay>1h</delay>
                    <history>7d</history>
                    <trends>30d</trends>
                    <status>0</status>
                    <value_type>0</value_type>
                    <allowed_hosts/>
                    <units/>
                    <snmpv3_contextname/>
                    <snmpv3_securityname/>
                    <snmpv3_securitylevel>0</snmpv3_securitylevel>
                    <snmpv3_authprotocol>0</snmpv3_authprotocol>
                    <snmpv3_authpassphrase/>
                    <snmpv3_privprotocol>0</snmpv3_privprotocol>
                    <snmpv3_privpassphrase/>
                    <params/>
                    <ipmi_sensor/>
                    <authtype>0</authtype>
                    <username/>
                    <password/>
                    <publickey/>
                    <privatekey/>
                    <port>161</port>
                    <description>Black Toner level now.</description>
                    <inventory_link>0</inventory_link>
                    <applications/>
                    <valuemap/>
                    <logtimefmt/>
                    <preprocessing/>
                    <jmx_endpoint/>
                    <timeout>3s</timeout>
                    <url/>
                    <query_fields/>
                    <posts/>
                    <status_codes>200</status_codes>
                    <follow_redirects>1</follow_redirects>
                    <post_type>0</post_type>
                    <http_proxy/>
                    <headers/>
                    <retrieve_mode>0</retrieve_mode>
                    <request_method>0</request_method>
                    <output_format>0</output_format>
                    <allow_traps>0</allow_traps>
                    <ssl_cert_file/>
                    <ssl_key_file/>
                    <ssl_key_password/>
                    <verify_peer>0</verify_peer>
                    <verify_host>0</verify_host>
                    <master_item/>
                </item>
                <item>
                    <name>Toner.Black.level.now %</name>
                    <type>15</type>
                    <snmp_community/>
                    <snmp_oid/>
                    <key>Toner.Black.level.now-percent</key>
                    <delay>1h</delay>
                    <history>90d</history>
                    <trends>365d</trends>
                    <status>0</status>
                    <value_type>3</value_type>
                    <allowed_hosts/>
                    <units/>
                    <snmpv3_contextname/>
                    <snmpv3_securityname/>
                    <snmpv3_securitylevel>0</snmpv3_securitylevel>
                    <snmpv3_authprotocol>0</snmpv3_authprotocol>
                    <snmpv3_authpassphrase/>
                    <snmpv3_privprotocol>0</snmpv3_privprotocol>
                    <snmpv3_privpassphrase/>
                    <params>100*last(&quot;Toner.Black.level.now&quot;)/last(&quot;Toner.Black.level.max&quot;)</params>
                    <ipmi_sensor/>
                    <authtype>0</authtype>
                    <username/>
                    <password/>
                    <publickey/>
                    <privatekey/>
                    <port/>
                    <description/>
                    <inventory_link>0</inventory_link>
                    <applications/>
                    <valuemap/>
                    <logtimefmt/>
                    <preprocessing/>
                    <jmx_endpoint/>
                    <timeout>3s</timeout>
                    <url/>
                    <query_fields/>
                    <posts/>
                    <status_codes>200</status_codes>
                    <follow_redirects>1</follow_redirects>
                    <post_type>0</post_type>
                    <http_proxy/>
                    <headers/>
                    <retrieve_mode>0</retrieve_mode>
                    <request_method>0</request_method>
                    <output_format>0</output_format>
                    <allow_traps>0</allow_traps>
                    <ssl_cert_file/>
                    <ssl_key_file/>
                    <ssl_key_password/>
                    <verify_peer>0</verify_peer>
                    <verify_host>0</verify_host>
                    <master_item/>
                </item>
                <item>
                    <name>Toner.Cyan.level.max</name>
                    <type>1</type>
                    <snmp_community>public</snmp_community>
                    <snmp_oid>.1.3.6.1.2.1.43.11.1.1.8.1.1</snmp_oid>
                    <key>Toner.Cyan.level.max</key>
                    <delay>3h</delay>
                    <history>7d</history>
                    <trends>30d</trends>
                    <status>0</status>
                    <value_type>0</value_type>
                    <allowed_hosts/>
                    <units/>
                    <snmpv3_contextname/>
                    <snmpv3_securityname/>
                    <snmpv3_securitylevel>0</snmpv3_securitylevel>
                    <snmpv3_authprotocol>0</snmpv3_authprotocol>
                    <snmpv3_authpassphrase/>
                    <snmpv3_privprotocol>0</snmpv3_privprotocol>
                    <snmpv3_privpassphrase/>
                    <params/>
                    <ipmi_sensor/>
                    <authtype>0</authtype>
                    <username/>
                    <password/>
                    <publickey/>
                    <privatekey/>
                    <port>161</port>
                    <description>Max Nuber of Cyan toner.</description>
                    <inventory_link>0</inventory_link>
                    <applications/>
                    <valuemap/>
                    <logtimefmt/>
                    <preprocessing/>
                    <jmx_endpoint/>
                    <timeout>3s</timeout>
                    <url/>
                    <query_fields/>
                    <posts/>
                    <status_codes>200</status_codes>
                    <follow_redirects>1</follow_redirects>
                    <post_type>0</post_type>
                    <http_proxy/>
                    <headers/>
                    <retrieve_mode>0</retrieve_mode>
                    <request_method>0</request_method>
                    <output_format>0</output_format>
                    <allow_traps>0</allow_traps>
                    <ssl_cert_file/>
                    <ssl_key_file/>
                    <ssl_key_password/>
                    <verify_peer>0</verify_peer>
                    <verify_host>0</verify_host>
                    <master_item/>
                </item>
                <item>
                    <name>Toner.Cyan.level.now</name>
                    <type>1</type>
                    <snmp_community>public</snmp_community>
                    <snmp_oid>.1.3.6.1.2.1.43.11.1.1.9.1.1</snmp_oid>
                    <key>Toner.Cyan.level.now</key>
                    <delay>1h</delay>
                    <history>7d</history>
                    <trends>30d</trends>
                    <status>0</status>
                    <value_type>0</value_type>
                    <allowed_hosts/>
                    <units/>
                    <snmpv3_contextname/>
                    <snmpv3_securityname/>
                    <snmpv3_securitylevel>0</snmpv3_securitylevel>
                    <snmpv3_authprotocol>0</snmpv3_authprotocol>
                    <snmpv3_authpassphrase/>
                    <snmpv3_privprotocol>0</snmpv3_privprotocol>
                    <snmpv3_privpassphrase/>
                    <params/>
                    <ipmi_sensor/>
                    <authtype>0</authtype>
                    <username/>
                    <password/>
                    <publickey/>
                    <privatekey/>
                    <port>161</port>
                    <description>Cyan Toner level now.</description>
                    <inventory_link>0</inventory_link>
                    <applications/>
                    <valuemap/>
                    <logtimefmt/>
                    <preprocessing/>
                    <jmx_endpoint/>
                    <timeout>3s</timeout>
                    <url/>
                    <query_fields/>
                    <posts/>
                    <status_codes>200</status_codes>
                    <follow_redirects>1</follow_redirects>
                    <post_type>0</post_type>
                    <http_proxy/>
                    <headers/>
                    <retrieve_mode>0</retrieve_mode>
                    <request_method>0</request_method>
                    <output_format>0</output_format>
                    <allow_traps>0</allow_traps>
                    <ssl_cert_file/>
                    <ssl_key_file/>
                    <ssl_key_password/>
                    <verify_peer>0</verify_peer>
                    <verify_host>0</verify_host>
                    <master_item/>
                </item>
                <item>
                    <name>Toner.Cyan.level.now %</name>
                    <type>15</type>
                    <snmp_community/>
                    <snmp_oid/>
                    <key>Toner.Cyan.level.now-percent</key>
                    <delay>1h</delay>
                    <history>90d</history>
                    <trends>365d</trends>
                    <status>0</status>
                    <value_type>3</value_type>
                    <allowed_hosts/>
                    <units/>
                    <snmpv3_contextname/>
                    <snmpv3_securityname/>
                    <snmpv3_securitylevel>0</snmpv3_securitylevel>
                    <snmpv3_authprotocol>0</snmpv3_authprotocol>
                    <snmpv3_authpassphrase/>
                    <snmpv3_privprotocol>0</snmpv3_privprotocol>
                    <snmpv3_privpassphrase/>
                    <params>100*last(&quot;Toner.Cyan.level.now&quot;)/last(&quot;Toner.Cyan.level.max&quot;)</params>
                    <ipmi_sensor/>
                    <authtype>0</authtype>
                    <username/>
                    <password/>
                    <publickey/>
                    <privatekey/>
                    <port/>
                    <description/>
                    <inventory_link>0</inventory_link>
                    <applications/>
                    <valuemap/>
                    <logtimefmt/>
                    <preprocessing/>
                    <jmx_endpoint/>
                    <timeout>3s</timeout>
                    <url/>
                    <query_fields/>
                    <posts/>
                    <status_codes>200</status_codes>
                    <follow_redirects>1</follow_redirects>
                    <post_type>0</post_type>
                    <http_proxy/>
                    <headers/>
                    <retrieve_mode>0</retrieve_mode>
                    <request_method>0</request_method>
                    <output_format>0</output_format>
                    <allow_traps>0</allow_traps>
                    <ssl_cert_file/>
                    <ssl_key_file/>
                    <ssl_key_password/>
                    <verify_peer>0</verify_peer>
                    <verify_host>0</verify_host>
                    <master_item/>
                </item>
                <item>
                    <name>Toner.Magenta.level.max</name>
                    <type>1</type>
                    <snmp_community>public</snmp_community>
                    <snmp_oid>.1.3.6.1.2.1.43.11.1.1.8.1.2</snmp_oid>
                    <key>Toner.Magenta.level.max</key>
                    <delay>3h</delay>
                    <history>7d</history>
                    <trends>30d</trends>
                    <status>0</status>
                    <value_type>0</value_type>
                    <allowed_hosts/>
                    <units/>
                    <snmpv3_contextname/>
                    <snmpv3_securityname/>
                    <snmpv3_securitylevel>0</snmpv3_securitylevel>
                    <snmpv3_authprotocol>0</snmpv3_authprotocol>
                    <snmpv3_authpassphrase/>
                    <snmpv3_privprotocol>0</snmpv3_privprotocol>
                    <snmpv3_privpassphrase/>
                    <params/>
                    <ipmi_sensor/>
                    <authtype>0</authtype>
                    <username/>
                    <password/>
                    <publickey/>
                    <privatekey/>
                    <port>161</port>
                    <description>Max Nuber of Magenta toner.</description>
                    <inventory_link>0</inventory_link>
                    <applications/>
                    <valuemap/>
                    <logtimefmt/>
                    <preprocessing/>
                    <jmx_endpoint/>
                    <timeout>3s</timeout>
                    <url/>
                    <query_fields/>
                    <posts/>
                    <status_codes>200</status_codes>
                    <follow_redirects>1</follow_redirects>
                    <post_type>0</post_type>
                    <http_proxy/>
                    <headers/>
                    <retrieve_mode>0</retrieve_mode>
                    <request_method>0</request_method>
                    <output_format>0</output_format>
                    <allow_traps>0</allow_traps>
                    <ssl_cert_file/>
                    <ssl_key_file/>
                    <ssl_key_password/>
                    <verify_peer>0</verify_peer>
                    <verify_host>0</verify_host>
                    <master_item/>
                </item>
                <item>
                    <name>Toner.Magenta.level.now</name>
                    <type>1</type>
                    <snmp_community>public</snmp_community>
                    <snmp_oid>.1.3.6.1.2.1.43.11.1.1.9.1.2</snmp_oid>
                    <key>Toner.Magenta.level.now</key>
                    <delay>1h</delay>
                    <history>7d</history>
                    <trends>30d</trends>
                    <status>0</status>
                    <value_type>0</value_type>
                    <allowed_hosts/>
                    <units/>
                    <snmpv3_contextname/>
                    <snmpv3_securityname/>
                    <snmpv3_securitylevel>0</snmpv3_securitylevel>
                    <snmpv3_authprotocol>0</snmpv3_authprotocol>
                    <snmpv3_authpassphrase/>
                    <snmpv3_privprotocol>0</snmpv3_privprotocol>
                    <snmpv3_privpassphrase/>
                    <params/>
                    <ipmi_sensor/>
                    <authtype>0</authtype>
                    <username/>
                    <password/>
                    <publickey/>
                    <privatekey/>
                    <port>161</port>
                    <description>Magenta Toner level now.</description>
                    <inventory_link>0</inventory_link>
                    <applications/>
                    <valuemap/>
                    <logtimefmt/>
                    <preprocessing/>
                    <jmx_endpoint/>
                    <timeout>3s</timeout>
                    <url/>
                    <query_fields/>
                    <posts/>
                    <status_codes>200</status_codes>
                    <follow_redirects>1</follow_redirects>
                    <post_type>0</post_type>
                    <http_proxy/>
                    <headers/>
                    <retrieve_mode>0</retrieve_mode>
                    <request_method>0</request_method>
                    <output_format>0</output_format>
                    <allow_traps>0</allow_traps>
                    <ssl_cert_file/>
                    <ssl_key_file/>
                    <ssl_key_password/>
                    <verify_peer>0</verify_peer>
                    <verify_host>0</verify_host>
                    <master_item/>
                </item>
                <item>
                    <name>Toner.Magenta.level.now %</name>
                    <type>15</type>
                    <snmp_community/>
                    <snmp_oid/>
                    <key>Toner.Magenta.level.now-percent</key>
                    <delay>1h</delay>
                    <history>90d</history>
                    <trends>365d</trends>
                    <status>0</status>
                    <value_type>3</value_type>
                    <allowed_hosts/>
                    <units/>
                    <snmpv3_contextname/>
                    <snmpv3_securityname/>
                    <snmpv3_securitylevel>0</snmpv3_securitylevel>
                    <snmpv3_authprotocol>0</snmpv3_authprotocol>
                    <snmpv3_authpassphrase/>
                    <snmpv3_privprotocol>0</snmpv3_privprotocol>
                    <snmpv3_privpassphrase/>
                    <params>100*last(&quot;Toner.Magenta.level.now&quot;)/last(&quot;Toner.Magenta.level.max&quot;)</params>
                    <ipmi_sensor/>
                    <authtype>0</authtype>
                    <username/>
                    <password/>
                    <publickey/>
                    <privatekey/>
                    <port/>
                    <description/>
                    <inventory_link>0</inventory_link>
                    <applications/>
                    <valuemap/>
                    <logtimefmt/>
                    <preprocessing/>
                    <jmx_endpoint/>
                    <timeout>3s</timeout>
                    <url/>
                    <query_fields/>
                    <posts/>
                    <status_codes>200</status_codes>
                    <follow_redirects>1</follow_redirects>
                    <post_type>0</post_type>
                    <http_proxy/>
                    <headers/>
                    <retrieve_mode>0</retrieve_mode>
                    <request_method>0</request_method>
                    <output_format>0</output_format>
                    <allow_traps>0</allow_traps>
                    <ssl_cert_file/>
                    <ssl_key_file/>
                    <ssl_key_password/>
                    <verify_peer>0</verify_peer>
                    <verify_host>0</verify_host>
                    <master_item/>
                </item>
                <item>
                    <name>Toner.MattBlack1.level.max</name>
                    <type>1</type>
                    <snmp_community>public</snmp_community>
                    <snmp_oid>.1.3.6.1.2.1.43.11.1.1.8.1.4</snmp_oid>
                    <key>Toner.MattBlack1.level.max</key>
                    <delay>3h</delay>
                    <history>7d</history>
                    <trends>30d</trends>
                    <status>0</status>
                    <value_type>0</value_type>
                    <allowed_hosts/>
                    <units/>
                    <snmpv3_contextname/>
                    <snmpv3_securityname/>
                    <snmpv3_securitylevel>0</snmpv3_securitylevel>
                    <snmpv3_authprotocol>0</snmpv3_authprotocol>
                    <snmpv3_authpassphrase/>
                    <snmpv3_privprotocol>0</snmpv3_privprotocol>
                    <snmpv3_privpassphrase/>
                    <params/>
                    <ipmi_sensor/>
                    <authtype>0</authtype>
                    <username/>
                    <password/>
                    <publickey/>
                    <privatekey/>
                    <port>161</port>
                    <description>Max Nuber of Black toner.</description>
                    <inventory_link>0</inventory_link>
                    <applications/>
                    <valuemap/>
                    <logtimefmt/>
                    <preprocessing/>
                    <jmx_endpoint/>
                    <timeout>3s</timeout>
                    <url/>
                    <query_fields/>
                    <posts/>
                    <status_codes>200</status_codes>
                    <follow_redirects>1</follow_redirects>
                    <post_type>0</post_type>
                    <http_proxy/>
                    <headers/>
                    <retrieve_mode>0</retrieve_mode>
                    <request_method>0</request_method>
                    <output_format>0</output_format>
                    <allow_traps>0</allow_traps>
                    <ssl_cert_file/>
                    <ssl_key_file/>
                    <ssl_key_password/>
                    <verify_peer>0</verify_peer>
                    <verify_host>0</verify_host>
                    <master_item/>
                </item>
                <item>
                    <name>Toner.MattBlack1.level.now</name>
                    <type>1</type>
                    <snmp_community>public</snmp_community>
                    <snmp_oid>.1.3.6.1.2.1.43.11.1.1.9.1.4</snmp_oid>
                    <key>Toner.MattBlack1.level.now</key>
                    <delay>1h</delay>
                    <history>7d</history>
                    <trends>30d</trends>
                    <status>0</status>
                    <value_type>0</value_type>
                    <allowed_hosts/>
                    <units/>
                    <snmpv3_contextname/>
                    <snmpv3_securityname/>
                    <snmpv3_securitylevel>0</snmpv3_securitylevel>
                    <snmpv3_authprotocol>0</snmpv3_authprotocol>
                    <snmpv3_authpassphrase/>
                    <snmpv3_privprotocol>0</snmpv3_privprotocol>
                    <snmpv3_privpassphrase/>
                    <params/>
                    <ipmi_sensor/>
                    <authtype>0</authtype>
                    <username/>
                    <password/>
                    <publickey/>
                    <privatekey/>
                    <port>161</port>
                    <description>Black Toner level now.</description>
                    <inventory_link>0</inventory_link>
                    <applications/>
                    <valuemap/>
                    <logtimefmt/>
                    <preprocessing/>
                    <jmx_endpoint/>
                    <timeout>3s</timeout>
                    <url/>
                    <query_fields/>
                    <posts/>
                    <status_codes>200</status_codes>
                    <follow_redirects>1</follow_redirects>
                    <post_type>0</post_type>
                    <http_proxy/>
                    <headers/>
                    <retrieve_mode>0</retrieve_mode>
                    <request_method>0</request_method>
                    <output_format>0</output_format>
                    <allow_traps>0</allow_traps>
                    <ssl_cert_file/>
                    <ssl_key_file/>
                    <ssl_key_password/>
                    <verify_peer>0</verify_peer>
                    <verify_host>0</verify_host>
                    <master_item/>
                </item>
                <item>
                    <name>Toner.MattBlack1.level.now %</name>
                    <type>15</type>
                    <snmp_community/>
                    <snmp_oid/>
                    <key>Toner.MattBlack1.level.now-percent</key>
                    <delay>1h</delay>
                    <history>90d</history>
                    <trends>365d</trends>
                    <status>0</status>
                    <value_type>3</value_type>
                    <allowed_hosts/>
                    <units/>
                    <snmpv3_contextname/>
                    <snmpv3_securityname/>
                    <snmpv3_securitylevel>0</snmpv3_securitylevel>
                    <snmpv3_authprotocol>0</snmpv3_authprotocol>
                    <snmpv3_authpassphrase/>
                    <snmpv3_privprotocol>0</snmpv3_privprotocol>
                    <snmpv3_privpassphrase/>
                    <params>100*last(&quot;Toner.MattBlack1.level.now&quot;)/last(&quot;Toner.MattBlack1.level.max&quot;)</params>
                    <ipmi_sensor/>
                    <authtype>0</authtype>
                    <username/>
                    <password/>
                    <publickey/>
                    <privatekey/>
                    <port/>
                    <description/>
                    <inventory_link>0</inventory_link>
                    <applications/>
                    <valuemap/>
                    <logtimefmt/>
                    <preprocessing/>
                    <jmx_endpoint/>
                    <timeout>3s</timeout>
                    <url/>
                    <query_fields/>
                    <posts/>
                    <status_codes>200</status_codes>
                    <follow_redirects>1</follow_redirects>
                    <post_type>0</post_type>
                    <http_proxy/>
                    <headers/>
                    <retrieve_mode>0</retrieve_mode>
                    <request_method>0</request_method>
                    <output_format>0</output_format>
                    <allow_traps>0</allow_traps>
                    <ssl_cert_file/>
                    <ssl_key_file/>
                    <ssl_key_password/>
                    <verify_peer>0</verify_peer>
                    <verify_host>0</verify_host>
                    <master_item/>
                </item>
                <item>
                    <name>Toner.MattBlack2.level.max</name>
                    <type>1</type>
                    <snmp_community>public</snmp_community>
                    <snmp_oid>.1.3.6.1.2.1.43.11.1.1.8.1.5</snmp_oid>
                    <key>Toner.MattBlack2.level.max</key>
                    <delay>3h</delay>
                    <history>7d</history>
                    <trends>30d</trends>
                    <status>0</status>
                    <value_type>0</value_type>
                    <allowed_hosts/>
                    <units/>
                    <snmpv3_contextname/>
                    <snmpv3_securityname/>
                    <snmpv3_securitylevel>0</snmpv3_securitylevel>
                    <snmpv3_authprotocol>0</snmpv3_authprotocol>
                    <snmpv3_authpassphrase/>
                    <snmpv3_privprotocol>0</snmpv3_privprotocol>
                    <snmpv3_privpassphrase/>
                    <params/>
                    <ipmi_sensor/>
                    <authtype>0</authtype>
                    <username/>
                    <password/>
                    <publickey/>
                    <privatekey/>
                    <port>161</port>
                    <description>Max Nuber of Black toner.</description>
                    <inventory_link>0</inventory_link>
                    <applications/>
                    <valuemap/>
                    <logtimefmt/>
                    <preprocessing/>
                    <jmx_endpoint/>
                    <timeout>3s</timeout>
                    <url/>
                    <query_fields/>
                    <posts/>
                    <status_codes>200</status_codes>
                    <follow_redirects>1</follow_redirects>
                    <post_type>0</post_type>
                    <http_proxy/>
                    <headers/>
                    <retrieve_mode>0</retrieve_mode>
                    <request_method>0</request_method>
                    <output_format>0</output_format>
                    <allow_traps>0</allow_traps>
                    <ssl_cert_file/>
                    <ssl_key_file/>
                    <ssl_key_password/>
                    <verify_peer>0</verify_peer>
                    <verify_host>0</verify_host>
                    <master_item/>
                </item>
                <item>
                    <name>Toner.MattBlack2.level.now</name>
                    <type>1</type>
                    <snmp_community>public</snmp_community>
                    <snmp_oid>.1.3.6.1.2.1.43.11.1.1.9.1.5</snmp_oid>
                    <key>Toner.MattBlack2.level.now</key>
                    <delay>1h</delay>
                    <history>7d</history>
                    <trends>30d</trends>
                    <status>0</status>
                    <value_type>0</value_type>
                    <allowed_hosts/>
                    <units/>
                    <snmpv3_contextname/>
                    <snmpv3_securityname/>
                    <snmpv3_securitylevel>0</snmpv3_securitylevel>
                    <snmpv3_authprotocol>0</snmpv3_authprotocol>
                    <snmpv3_authpassphrase/>
                    <snmpv3_privprotocol>0</snmpv3_privprotocol>
                    <snmpv3_privpassphrase/>
                    <params/>
                    <ipmi_sensor/>
                    <authtype>0</authtype>
                    <username/>
                    <password/>
                    <publickey/>
                    <privatekey/>
                    <port>161</port>
                    <description>Black Toner level now.</description>
                    <inventory_link>0</inventory_link>
                    <applications/>
                    <valuemap/>
                    <logtimefmt/>
                    <preprocessing/>
                    <jmx_endpoint/>
                    <timeout>3s</timeout>
                    <url/>
                    <query_fields/>
                    <posts/>
                    <status_codes>200</status_codes>
                    <follow_redirects>1</follow_redirects>
                    <post_type>0</post_type>
                    <http_proxy/>
                    <headers/>
                    <retrieve_mode>0</retrieve_mode>
                    <request_method>0</request_method>
                    <output_format>0</output_format>
                    <allow_traps>0</allow_traps>
                    <ssl_cert_file/>
                    <ssl_key_file/>
                    <ssl_key_password/>
                    <verify_peer>0</verify_peer>
                    <verify_host>0</verify_host>
                    <master_item/>
                </item>
                <item>
                    <name>Toner.MattBlack2.level.now %</name>
                    <type>15</type>
                    <snmp_community/>
                    <snmp_oid/>
                    <key>Toner.MattBlack2.level.now-percent</key>
                    <delay>1h</delay>
                    <history>90d</history>
                    <trends>365d</trends>
                    <status>0</status>
                    <value_type>3</value_type>
                    <allowed_hosts/>
                    <units/>
                    <snmpv3_contextname/>
                    <snmpv3_securityname/>
                    <snmpv3_securitylevel>0</snmpv3_securitylevel>
                    <snmpv3_authprotocol>0</snmpv3_authprotocol>
                    <snmpv3_authpassphrase/>
                    <snmpv3_privprotocol>0</snmpv3_privprotocol>
                    <snmpv3_privpassphrase/>
                    <params>100*last(&quot;Toner.MattBlack2.level.now&quot;)/last(&quot;Toner.MattBlack2.level.max&quot;)</params>
                    <ipmi_sensor/>
                    <authtype>0</authtype>
                    <username/>
                    <password/>
                    <publickey/>
                    <privatekey/>
                    <port/>
                    <description/>
                    <inventory_link>0</inventory_link>
                    <applications/>
                    <valuemap/>
                    <logtimefmt/>
                    <preprocessing/>
                    <jmx_endpoint/>
                    <timeout>3s</timeout>
                    <url/>
                    <query_fields/>
                    <posts/>
                    <status_codes>200</status_codes>
                    <follow_redirects>1</follow_redirects>
                    <post_type>0</post_type>
                    <http_proxy/>
                    <headers/>
                    <retrieve_mode>0</retrieve_mode>
                    <request_method>0</request_method>
                    <output_format>0</output_format>
                    <allow_traps>0</allow_traps>
                    <ssl_cert_file/>
                    <ssl_key_file/>
                    <ssl_key_password/>
                    <verify_peer>0</verify_peer>
                    <verify_host>0</verify_host>
                    <master_item/>
                </item>
                <item>
                    <name>Toner.WasteInkTank.level.max</name>
                    <type>1</type>
                    <snmp_community>public</snmp_community>
                    <snmp_oid>.1.3.6.1.2.1.43.11.1.1.8.1.7</snmp_oid>
                    <key>Toner.WasteInkTank.level.max</key>
                    <delay>3h</delay>
                    <history>7d</history>
                    <trends>30d</trends>
                    <status>0</status>
                    <value_type>0</value_type>
                    <allowed_hosts/>
                    <units/>
                    <snmpv3_contextname/>
                    <snmpv3_securityname/>
                    <snmpv3_securitylevel>0</snmpv3_securitylevel>
                    <snmpv3_authprotocol>0</snmpv3_authprotocol>
                    <snmpv3_authpassphrase/>
                    <snmpv3_privprotocol>0</snmpv3_privprotocol>
                    <snmpv3_privpassphrase/>
                    <params/>
                    <ipmi_sensor/>
                    <authtype>0</authtype>
                    <username/>
                    <password/>
                    <publickey/>
                    <privatekey/>
                    <port>161</port>
                    <description>Max Nuber of WasteInkTank toner.</description>
                    <inventory_link>0</inventory_link>
                    <applications/>
                    <valuemap/>
                    <logtimefmt/>
                    <preprocessing/>
                    <jmx_endpoint/>
                    <timeout>3s</timeout>
                    <url/>
                    <query_fields/>
                    <posts/>
                    <status_codes>200</status_codes>
                    <follow_redirects>1</follow_redirects>
                    <post_type>0</post_type>
                    <http_proxy/>
                    <headers/>
                    <retrieve_mode>0</retrieve_mode>
                    <request_method>0</request_method>
                    <output_format>0</output_format>
                    <allow_traps>0</allow_traps>
                    <ssl_cert_file/>
                    <ssl_key_file/>
                    <ssl_key_password/>
                    <verify_peer>0</verify_peer>
                    <verify_host>0</verify_host>
                    <master_item/>
                </item>
                <item>
                    <name>Toner.WasteInkTank.level.now</name>
                    <type>1</type>
                    <snmp_community>public</snmp_community>
                    <snmp_oid>.1.3.6.1.2.1.43.11.1.1.9.1.7</snmp_oid>
                    <key>Toner.WasteInkTank.level.now</key>
                    <delay>1h</delay>
                    <history>7d</history>
                    <trends>30d</trends>
                    <status>0</status>
                    <value_type>0</value_type>
                    <allowed_hosts/>
                    <units/>
                    <snmpv3_contextname/>
                    <snmpv3_securityname/>
                    <snmpv3_securitylevel>0</snmpv3_securitylevel>
                    <snmpv3_authprotocol>0</snmpv3_authprotocol>
                    <snmpv3_authpassphrase/>
                    <snmpv3_privprotocol>0</snmpv3_privprotocol>
                    <snmpv3_privpassphrase/>
                    <params/>
                    <ipmi_sensor/>
                    <authtype>0</authtype>
                    <username/>
                    <password/>
                    <publickey/>
                    <privatekey/>
                    <port>161</port>
                    <description>Now Nuber of WasteInkTank toner.</description>
                    <inventory_link>0</inventory_link>
                    <applications/>
                    <valuemap/>
                    <logtimefmt/>
                    <preprocessing/>
                    <jmx_endpoint/>
                    <timeout>3s</timeout>
                    <url/>
                    <query_fields/>
                    <posts/>
                    <status_codes>200</status_codes>
                    <follow_redirects>1</follow_redirects>
                    <post_type>0</post_type>
                    <http_proxy/>
                    <headers/>
                    <retrieve_mode>0</retrieve_mode>
                    <request_method>0</request_method>
                    <output_format>0</output_format>
                    <allow_traps>0</allow_traps>
                    <ssl_cert_file/>
                    <ssl_key_file/>
                    <ssl_key_password/>
                    <verify_peer>0</verify_peer>
                    <verify_host>0</verify_host>
                    <master_item/>
                </item>
                <item>
                    <name>Toner.WasteInkTank.level.now %</name>
                    <type>15</type>
                    <snmp_community/>
                    <snmp_oid/>
                    <key>Toner.WasteInkTank.level.now-percent</key>
                    <delay>1h</delay>
                    <history>90d</history>
                    <trends>365d</trends>
                    <status>0</status>
                    <value_type>3</value_type>
                    <allowed_hosts/>
                    <units/>
                    <snmpv3_contextname/>
                    <snmpv3_securityname/>
                    <snmpv3_securitylevel>0</snmpv3_securitylevel>
                    <snmpv3_authprotocol>0</snmpv3_authprotocol>
                    <snmpv3_authpassphrase/>
                    <snmpv3_privprotocol>0</snmpv3_privprotocol>
                    <snmpv3_privpassphrase/>
                    <params>100*last(&quot;Toner.WasteInkTank.level.now&quot;)/last(&quot;Toner.WasteInkTank.level.max&quot;)</params>
                    <ipmi_sensor/>
                    <authtype>0</authtype>
                    <username/>
                    <password/>
                    <publickey/>
                    <privatekey/>
                    <port/>
                    <description/>
                    <inventory_link>0</inventory_link>
                    <applications/>
                    <valuemap/>
                    <logtimefmt/>
                    <preprocessing/>
                    <jmx_endpoint/>
                    <timeout>3s</timeout>
                    <url/>
                    <query_fields/>
                    <posts/>
                    <status_codes>200</status_codes>
                    <follow_redirects>1</follow_redirects>
                    <post_type>0</post_type>
                    <http_proxy/>
                    <headers/>
                    <retrieve_mode>0</retrieve_mode>
                    <request_method>0</request_method>
                    <output_format>0</output_format>
                    <allow_traps>0</allow_traps>
                    <ssl_cert_file/>
                    <ssl_key_file/>
                    <ssl_key_password/>
                    <verify_peer>0</verify_peer>
                    <verify_host>0</verify_host>
                    <master_item/>
                </item>
                <item>
                    <name>Toner.Yellow.level.max</name>
                    <type>1</type>
                    <snmp_community>public</snmp_community>
                    <snmp_oid>.1.3.6.1.2.1.43.11.1.1.8.1.3</snmp_oid>
                    <key>Toner.Yellow.level.max</key>
                    <delay>3h</delay>
                    <history>7d</history>
                    <trends>30d</trends>
                    <status>0</status>
                    <value_type>0</value_type>
                    <allowed_hosts/>
                    <units/>
                    <snmpv3_contextname/>
                    <snmpv3_securityname/>
                    <snmpv3_securitylevel>0</snmpv3_securitylevel>
                    <snmpv3_authprotocol>0</snmpv3_authprotocol>
                    <snmpv3_authpassphrase/>
                    <snmpv3_privprotocol>0</snmpv3_privprotocol>
                    <snmpv3_privpassphrase/>
                    <params/>
                    <ipmi_sensor/>
                    <authtype>0</authtype>
                    <username/>
                    <password/>
                    <publickey/>
                    <privatekey/>
                    <port>161</port>
                    <description>Max Nuber of Yellow toner.</description>
                    <inventory_link>0</inventory_link>
                    <applications/>
                    <valuemap/>
                    <logtimefmt/>
                    <preprocessing/>
                    <jmx_endpoint/>
                    <timeout>3s</timeout>
                    <url/>
                    <query_fields/>
                    <posts/>
                    <status_codes>200</status_codes>
                    <follow_redirects>1</follow_redirects>
                    <post_type>0</post_type>
                    <http_proxy/>
                    <headers/>
                    <retrieve_mode>0</retrieve_mode>
                    <request_method>0</request_method>
                    <output_format>0</output_format>
                    <allow_traps>0</allow_traps>
                    <ssl_cert_file/>
                    <ssl_key_file/>
                    <ssl_key_password/>
                    <verify_peer>0</verify_peer>
                    <verify_host>0</verify_host>
                    <master_item/>
                </item>
                <item>
                    <name>Toner.Yellow.level.now</name>
                    <type>1</type>
                    <snmp_community>public</snmp_community>
                    <snmp_oid>.1.3.6.1.2.1.43.11.1.1.9.1.3</snmp_oid>
                    <key>Toner.Yellow.level.now</key>
                    <delay>1h</delay>
                    <history>7d</history>
                    <trends>30d</trends>
                    <status>0</status>
                    <value_type>0</value_type>
                    <allowed_hosts/>
                    <units/>
                    <snmpv3_contextname/>
                    <snmpv3_securityname/>
                    <snmpv3_securitylevel>0</snmpv3_securitylevel>
                    <snmpv3_authprotocol>0</snmpv3_authprotocol>
                    <snmpv3_authpassphrase/>
                    <snmpv3_privprotocol>0</snmpv3_privprotocol>
                    <snmpv3_privpassphrase/>
                    <params/>
                    <ipmi_sensor/>
                    <authtype>0</authtype>
                    <username/>
                    <password/>
                    <publickey/>
                    <privatekey/>
                    <port>161</port>
                    <description>Yellow Toner level now.</description>
                    <inventory_link>0</inventory_link>
                    <applications/>
                    <valuemap/>
                    <logtimefmt/>
                    <preprocessing/>
                    <jmx_endpoint/>
                    <timeout>3s</timeout>
                    <url/>
                    <query_fields/>
                    <posts/>
                    <status_codes>200</status_codes>
                    <follow_redirects>1</follow_redirects>
                    <post_type>0</post_type>
                    <http_proxy/>
                    <headers/>
                    <retrieve_mode>0</retrieve_mode>
                    <request_method>0</request_method>
                    <output_format>0</output_format>
                    <allow_traps>0</allow_traps>
                    <ssl_cert_file/>
                    <ssl_key_file/>
                    <ssl_key_password/>
                    <verify_peer>0</verify_peer>
                    <verify_host>0</verify_host>
                    <master_item/>
                </item>
                <item>
                    <name>Toner.Yellow.level.now %</name>
                    <type>15</type>
                    <snmp_community/>
                    <snmp_oid/>
                    <key>Toner.Yellow.level.now-percent</key>
                    <delay>1h</delay>
                    <history>90d</history>
                    <trends>365d</trends>
                    <status>0</status>
                    <value_type>3</value_type>
                    <allowed_hosts/>
                    <units/>
                    <snmpv3_contextname/>
                    <snmpv3_securityname/>
                    <snmpv3_securitylevel>0</snmpv3_securitylevel>
                    <snmpv3_authprotocol>0</snmpv3_authprotocol>
                    <snmpv3_authpassphrase/>
                    <snmpv3_privprotocol>0</snmpv3_privprotocol>
                    <snmpv3_privpassphrase/>
                    <params>100*last(&quot;Toner.Yellow.level.now&quot;)/last(&quot;Toner.Yellow.level.max&quot;)</params>
                    <ipmi_sensor/>
                    <authtype>0</authtype>
                    <username/>
                    <password/>
                    <publickey/>
                    <privatekey/>
                    <port/>
                    <description/>
                    <inventory_link>0</inventory_link>
                    <applications/>
                    <valuemap/>
                    <logtimefmt/>
                    <preprocessing/>
                    <jmx_endpoint/>
                    <timeout>3s</timeout>
                    <url/>
                    <query_fields/>
                    <posts/>
                    <status_codes>200</status_codes>
                    <follow_redirects>1</follow_redirects>
                    <post_type>0</post_type>
                    <http_proxy/>
                    <headers/>
                    <retrieve_mode>0</retrieve_mode>
                    <request_method>0</request_method>
                    <output_format>0</output_format>
                    <allow_traps>0</allow_traps>
                    <ssl_cert_file/>
                    <ssl_key_file/>
                    <ssl_key_password/>
                    <verify_peer>0</verify_peer>
                    <verify_host>0</verify_host>
                    <master_item/>
                </item>
                <item>
                    <name>WasteInkTank.toner.model</name>
                    <type>1</type>
                    <snmp_community>public</snmp_community>
                    <snmp_oid>.1.3.6.1.2.1.43.11.1.1.6.1.7</snmp_oid>
                    <key>WasteInkTank.toner.model</key>
                    <delay>6h</delay>
                    <history>7d</history>
                    <trends>0</trends>
                    <status>0</status>
                    <value_type>1</value_type>
                    <allowed_hosts/>
                    <units/>
                    <snmpv3_contextname/>
                    <snmpv3_securityname/>
                    <snmpv3_securitylevel>0</snmpv3_securitylevel>
                    <snmpv3_authprotocol>0</snmpv3_authprotocol>
                    <snmpv3_authpassphrase/>
                    <snmpv3_privprotocol>0</snmpv3_privprotocol>
                    <snmpv3_privpassphrase/>
                    <params/>
                    <ipmi_sensor/>
                    <authtype>0</authtype>
                    <username/>
                    <password/>
                    <publickey/>
                    <privatekey/>
                    <port>161</port>
                    <description>Shows printer toner model and name.&#13;
WasteInkTank</description>
                    <inventory_link>0</inventory_link>
                    <applications/>
                    <valuemap/>
                    <logtimefmt/>
                    <preprocessing/>
                    <jmx_endpoint/>
                    <timeout>3s</timeout>
                    <url/>
                    <query_fields/>
                    <posts/>
                    <status_codes>200</status_codes>
                    <follow_redirects>1</follow_redirects>
                    <post_type>0</post_type>
                    <http_proxy/>
                    <headers/>
                    <retrieve_mode>0</retrieve_mode>
                    <request_method>0</request_method>
                    <output_format>0</output_format>
                    <allow_traps>0</allow_traps>
                    <ssl_cert_file/>
                    <ssl_key_file/>
                    <ssl_key_password/>
                    <verify_peer>0</verify_peer>
                    <verify_host>0</verify_host>
                    <master_item/>
                </item>
                <item>
                    <name>YellowIPF.toner.model</name>
                    <type>1</type>
                    <snmp_community>public</snmp_community>
                    <snmp_oid>.1.3.6.1.2.1.43.11.1.1.6.1.3</snmp_oid>
                    <key>YellowIPF.toner.model</key>
                    <delay>6h</delay>
                    <history>7d</history>
                    <trends>0</trends>
                    <status>0</status>
                    <value_type>1</value_type>
                    <allowed_hosts/>
                    <units/>
                    <snmpv3_contextname/>
                    <snmpv3_securityname/>
                    <snmpv3_securitylevel>0</snmpv3_securitylevel>
                    <snmpv3_authprotocol>0</snmpv3_authprotocol>
                    <snmpv3_authpassphrase/>
                    <snmpv3_privprotocol>0</snmpv3_privprotocol>
                    <snmpv3_privpassphrase/>
                    <params/>
                    <ipmi_sensor/>
                    <authtype>0</authtype>
                    <username/>
                    <password/>
                    <publickey/>
                    <privatekey/>
                    <port>161</port>
                    <description>Shows printer magenta model and name.&#13;
YellowInkCartridge</description>
                    <inventory_link>0</inventory_link>
                    <applications/>
                    <valuemap/>
                    <logtimefmt/>
                    <preprocessing/>
                    <jmx_endpoint/>
                    <timeout>3s</timeout>
                    <url/>
                    <query_fields/>
                    <posts/>
                    <status_codes>200</status_codes>
                    <follow_redirects>1</follow_redirects>
                    <post_type>0</post_type>
                    <http_proxy/>
                    <headers/>
                    <retrieve_mode>0</retrieve_mode>
                    <request_method>0</request_method>
                    <output_format>0</output_format>
                    <allow_traps>0</allow_traps>
                    <ssl_cert_file/>
                    <ssl_key_file/>
                    <ssl_key_password/>
                    <verify_peer>0</verify_peer>
                    <verify_host>0</verify_host>
                    <master_item/>
                </item>
            </items>
            <discovery_rules/>
            <httptests/>
            <macros/>
            <templates>
                <template>
                    <name>Template Module Generic SNMPv1</name>
                </template>
            </templates>
            <screens/>
            <tags/>
        </template>
    </templates>
    <triggers>
        <trigger>
            <expression>{Template Canon IPF Color printers:Toner.Cyan.level.now.last()}&lt;20</expression>
            <recovery_mode>0</recovery_mode>
            <recovery_expression/>
            <name>   {HOSTNAME} (&lt;20%)</name>
            <correlation_mode>0</correlation_mode>
            <correlation_tag/>
            <url/>
            <status>0</status>
            <priority>1</priority>
            <description>Shows that cyan toner level reach 0.</description>
            <type>0</type>
            <manual_close>0</manual_close>
            <dependencies/>
            <tags/>
        </trigger>
        <trigger>
            <expression>{Template Canon IPF Color printers:Toner.Cyan.level.now.last()}&lt;10</expression>
            <recovery_mode>0</recovery_mode>
            <recovery_expression/>
            <name>   {HOSTNAME} (&lt;10%)</name>
            <correlation_mode>0</correlation_mode>
            <correlation_tag/>
            <url/>
            <status>0</status>
            <priority>2</priority>
            <description>Shows that cyan toner level reach 0.</description>
            <type>0</type>
            <manual_close>0</manual_close>
            <dependencies/>
            <tags/>
        </trigger>
        <trigger>
            <expression>{Template Canon IPF Color printers:Toner.Yellow.level.now.last()}&lt;20</expression>
            <recovery_mode>0</recovery_mode>
            <recovery_expression/>
            <name>   {HOSTNAME} (&lt;20%)</name>
            <correlation_mode>0</correlation_mode>
            <correlation_tag/>
            <url/>
            <status>0</status>
            <priority>1</priority>
            <description>Shows that yellow toner level reach 0.</description>
            <type>0</type>
            <manual_close>0</manual_close>
            <dependencies/>
            <tags/>
        </trigger>
        <trigger>
            <expression>{Template Canon IPF Color printers:Toner.Yellow.level.now.last()}&lt;10</expression>
            <recovery_mode>0</recovery_mode>
            <recovery_expression/>
            <name>   {HOSTNAME} (&lt;10%)</name>
            <correlation_mode>0</correlation_mode>
            <correlation_tag/>
            <url/>
            <status>0</status>
            <priority>2</priority>
            <description>Shows that yellow toner level reach 0.</description>
            <type>0</type>
            <manual_close>0</manual_close>
            <dependencies/>
            <tags/>
        </trigger>
        <trigger>
            <expression>{Template Canon IPF Color printers:Toner.MattBlack1.level.now.last()}&lt;20</expression>
            <recovery_mode>0</recovery_mode>
            <recovery_expression/>
            <name>  1   {HOSTNAME} (&lt;20%)</name>
            <correlation_mode>0</correlation_mode>
            <correlation_tag/>
            <url/>
            <status>0</status>
            <priority>1</priority>
            <description>Shows that black toner level reach 0.</description>
            <type>0</type>
            <manual_close>0</manual_close>
            <dependencies/>
            <tags/>
        </trigger>
        <trigger>
            <expression>{Template Canon IPF Color printers:Toner.MattBlack1.level.now.last()}&lt;10</expression>
            <recovery_mode>0</recovery_mode>
            <recovery_expression/>
            <name>  1   {HOSTNAME} (&lt;10%)</name>
            <correlation_mode>0</correlation_mode>
            <correlation_tag/>
            <url/>
            <status>0</status>
            <priority>2</priority>
            <description>Shows that black toner level reach 0.</description>
            <type>0</type>
            <manual_close>0</manual_close>
            <dependencies/>
            <tags/>
        </trigger>
        <trigger>
            <expression>{Template Canon IPF Color printers:Toner.MattBlack2.level.now.last()}&lt;20</expression>
            <recovery_mode>0</recovery_mode>
            <recovery_expression/>
            <name>  2   {HOSTNAME} (&lt;20%)</name>
            <correlation_mode>0</correlation_mode>
            <correlation_tag/>
            <url/>
            <status>0</status>
            <priority>1</priority>
            <description>Shows that black toner level reach 0.</description>
            <type>0</type>
            <manual_close>0</manual_close>
            <dependencies/>
            <tags/>
        </trigger>
        <trigger>
            <expression>{Template Canon IPF Color printers:Toner.MattBlack2.level.now.last()}&lt;10</expression>
            <recovery_mode>0</recovery_mode>
            <recovery_expression/>
            <name>  2   {HOSTNAME} (&lt;10%)</name>
            <correlation_mode>0</correlation_mode>
            <correlation_tag/>
            <url/>
            <status>0</status>
            <priority>2</priority>
            <description>Shows that black toner level reach 0.</description>
            <type>0</type>
            <manual_close>0</manual_close>
            <dependencies/>
            <tags/>
        </trigger>
        <trigger>
            <expression>{Template Canon IPF Color printers:Toner.Magenta.level.now.last()}&lt;20</expression>
            <recovery_mode>0</recovery_mode>
            <recovery_expression/>
            <name>   {HOSTNAME} (&lt;20%)</name>
            <correlation_mode>0</correlation_mode>
            <correlation_tag/>
            <url/>
            <status>0</status>
            <priority>1</priority>
            <description>Empty Magenta toner.</description>
            <type>0</type>
            <manual_close>0</manual_close>
            <dependencies/>
            <tags/>
        </trigger>
        <trigger>
            <expression>{Template Canon IPF Color printers:Toner.Magenta.level.now.last()}&lt;10</expression>
            <recovery_mode>0</recovery_mode>
            <recovery_expression/>
            <name>   {HOSTNAME} (&lt;10%)</name>
            <correlation_mode>0</correlation_mode>
            <correlation_tag/>
            <url/>
            <status>0</status>
            <priority>2</priority>
            <description>Empty Magenta toner.</description>
            <type>0</type>
            <manual_close>0</manual_close>
            <dependencies/>
            <tags/>
        </trigger>
        <trigger>
            <expression>{Template Canon IPF Color printers:Toner.Black.level.now.last()}&lt;20</expression>
            <recovery_mode>0</recovery_mode>
            <recovery_expression/>
            <name>   {HOSTNAME} (&lt;20%)</name>
            <correlation_mode>0</correlation_mode>
            <correlation_tag/>
            <url/>
            <status>0</status>
            <priority>1</priority>
            <description>Shows that black toner level reach 0.</description>
            <type>0</type>
            <manual_close>0</manual_close>
            <dependencies/>
            <tags/>
        </trigger>
        <trigger>
            <expression>{Template Canon IPF Color printers:Toner.Black.level.now.last()}&lt;10</expression>
            <recovery_mode>0</recovery_mode>
            <recovery_expression/>
            <name>   {HOSTNAME} (&lt;10%)</name>
            <correlation_mode>0</correlation_mode>
            <correlation_tag/>
            <url/>
            <status>0</status>
            <priority>2</priority>
            <description>Shows that black toner level reach 0.</description>
            <type>0</type>
            <manual_close>0</manual_close>
            <dependencies/>
            <tags/>
        </trigger>
    </triggers>
    <graphs>
        <graph>
            <name>    , %</name>
            <width>900</width>
            <height>200</height>
            <yaxismin>0.0000</yaxismin>
            <yaxismax>100.0000</yaxismax>
            <show_work_period>1</show_work_period>
            <show_triggers>1</show_triggers>
            <type>0</type>
            <show_legend>1</show_legend>
            <show_3d>0</show_3d>
            <percent_left>0.0000</percent_left>
            <percent_right>0.0000</percent_right>
            <ymin_type_1>0</ymin_type_1>
            <ymax_type_1>0</ymax_type_1>
            <ymin_item_1>0</ymin_item_1>
            <ymax_item_1>0</ymax_item_1>
            <graph_items>
                <graph_item>
                    <sortorder>0</sortorder>
                    <drawtype>1</drawtype>
                    <color>FFBF00</color>
                    <yaxisside>0</yaxisside>
                    <calc_fnc>2</calc_fnc>
                    <type>0</type>
                    <item>
                        <host>Template Canon IPF Color printers</host>
                        <key>Toner.WasteInkTank.level.now-percent</key>
                    </item>
                </graph_item>
            </graph_items>
        </graph>
        <graph>
            <name>    , %</name>
            <width>900</width>
            <height>200</height>
            <yaxismin>0.0000</yaxismin>
            <yaxismax>100.0000</yaxismax>
            <show_work_period>1</show_work_period>
            <show_triggers>1</show_triggers>
            <type>0</type>
            <show_legend>1</show_legend>
            <show_3d>0</show_3d>
            <percent_left>0.0000</percent_left>
            <percent_right>0.0000</percent_right>
            <ymin_type_1>1</ymin_type_1>
            <ymax_type_1>1</ymax_type_1>
            <ymin_item_1>0</ymin_item_1>
            <ymax_item_1>0</ymax_item_1>
            <graph_items>
                <graph_item>
                    <sortorder>0</sortorder>
                    <drawtype>1</drawtype>
                    <color>00BFFF</color>
                    <yaxisside>0</yaxisside>
                    <calc_fnc>2</calc_fnc>
                    <type>0</type>
                    <item>
                        <host>Template Canon IPF Color printers</host>
                        <key>Toner.Cyan.level.now-percent</key>
                    </item>
                </graph_item>
            </graph_items>
        </graph>
        <graph>
            <name>    , %</name>
            <width>900</width>
            <height>200</height>
            <yaxismin>0.0000</yaxismin>
            <yaxismax>100.0000</yaxismax>
            <show_work_period>1</show_work_period>
            <show_triggers>1</show_triggers>
            <type>0</type>
            <show_legend>1</show_legend>
            <show_3d>0</show_3d>
            <percent_left>0.0000</percent_left>
            <percent_right>0.0000</percent_right>
            <ymin_type_1>1</ymin_type_1>
            <ymax_type_1>1</ymax_type_1>
            <ymin_item_1>0</ymin_item_1>
            <ymax_item_1>0</ymax_item_1>
            <graph_items>
                <graph_item>
                    <sortorder>0</sortorder>
                    <drawtype>1</drawtype>
                    <color>FFFF00</color>
                    <yaxisside>0</yaxisside>
                    <calc_fnc>2</calc_fnc>
                    <type>0</type>
                    <item>
                        <host>Template Canon IPF Color printers</host>
                        <key>Toner.Yellow.level.now-percent</key>
                    </item>
                </graph_item>
            </graph_items>
        </graph>
        <graph>
            <name>    1  , %</name>
            <width>900</width>
            <height>200</height>
            <yaxismin>0.0000</yaxismin>
            <yaxismax>100.0000</yaxismax>
            <show_work_period>1</show_work_period>
            <show_triggers>1</show_triggers>
            <type>0</type>
            <show_legend>1</show_legend>
            <show_3d>0</show_3d>
            <percent_left>0.0000</percent_left>
            <percent_right>0.0000</percent_right>
            <ymin_type_1>1</ymin_type_1>
            <ymax_type_1>1</ymax_type_1>
            <ymin_item_1>0</ymin_item_1>
            <ymax_item_1>0</ymax_item_1>
            <graph_items>
                <graph_item>
                    <sortorder>0</sortorder>
                    <drawtype>1</drawtype>
                    <color>000000</color>
                    <yaxisside>0</yaxisside>
                    <calc_fnc>2</calc_fnc>
                    <type>0</type>
                    <item>
                        <host>Template Canon IPF Color printers</host>
                        <key>Toner.MattBlack1.level.now-percent</key>
                    </item>
                </graph_item>
            </graph_items>
        </graph>
        <graph>
            <name>    2  , %</name>
            <width>900</width>
            <height>200</height>
            <yaxismin>0.0000</yaxismin>
            <yaxismax>100.0000</yaxismax>
            <show_work_period>1</show_work_period>
            <show_triggers>1</show_triggers>
            <type>0</type>
            <show_legend>1</show_legend>
            <show_3d>0</show_3d>
            <percent_left>0.0000</percent_left>
            <percent_right>0.0000</percent_right>
            <ymin_type_1>1</ymin_type_1>
            <ymax_type_1>1</ymax_type_1>
            <ymin_item_1>0</ymin_item_1>
            <ymax_item_1>0</ymax_item_1>
            <graph_items>
                <graph_item>
                    <sortorder>0</sortorder>
                    <drawtype>1</drawtype>
                    <color>000000</color>
                    <yaxisside>0</yaxisside>
                    <calc_fnc>2</calc_fnc>
                    <type>0</type>
                    <item>
                        <host>Template Canon IPF Color printers</host>
                        <key>Toner.MattBlack2.level.now-percent</key>
                    </item>
                </graph_item>
            </graph_items>
        </graph>
        <graph>
            <name>    , %</name>
            <width>900</width>
            <height>200</height>
            <yaxismin>0.0000</yaxismin>
            <yaxismax>100.0000</yaxismax>
            <show_work_period>1</show_work_period>
            <show_triggers>1</show_triggers>
            <type>0</type>
            <show_legend>1</show_legend>
            <show_3d>0</show_3d>
            <percent_left>0.0000</percent_left>
            <percent_right>0.0000</percent_right>
            <ymin_type_1>1</ymin_type_1>
            <ymax_type_1>1</ymax_type_1>
            <ymin_item_1>0</ymin_item_1>
            <ymax_item_1>0</ymax_item_1>
            <graph_items>
                <graph_item>
                    <sortorder>0</sortorder>
                    <drawtype>1</drawtype>
                    <color>4000FF</color>
                    <yaxisside>0</yaxisside>
                    <calc_fnc>2</calc_fnc>
                    <type>0</type>
                    <item>
                        <host>Template Canon IPF Color printers</host>
                        <key>Toner.Magenta.level.now-percent</key>
                    </item>
                </graph_item>
            </graph_items>
        </graph>
        <graph>
            <name>    , %</name>
            <width>900</width>
            <height>200</height>
            <yaxismin>0.0000</yaxismin>
            <yaxismax>100.0000</yaxismax>
            <show_work_period>1</show_work_period>
            <show_triggers>1</show_triggers>
            <type>0</type>
            <show_legend>1</show_legend>
            <show_3d>0</show_3d>
            <percent_left>0.0000</percent_left>
            <percent_right>0.0000</percent_right>
            <ymin_type_1>1</ymin_type_1>
            <ymax_type_1>1</ymax_type_1>
            <ymin_item_1>0</ymin_item_1>
            <ymax_item_1>0</ymax_item_1>
            <graph_items>
                <graph_item>
                    <sortorder>0</sortorder>
                    <drawtype>1</drawtype>
                    <color>000000</color>
                    <yaxisside>0</yaxisside>
                    <calc_fnc>2</calc_fnc>
                    <type>0</type>
                    <item>
                        <host>Template Canon IPF Color printers</host>
                        <key>Toner.Black.level.now-percent</key>
                    </item>
                </graph_item>
            </graph_items>
        </graph>
    </graphs>
</zabbix_export>
