{
    "link_name": "Cisco SNMP v3 Interface Discovery",
    "type": "Template",
    "OS": "",
    "vendor": "Cisco",
    "minZabbVer": "4.4.x",
    "link_desc": "<p>Cisco SNMP v3 Discovery for Interface Monitoring</p>\n<p>Template use this macros:<br /><br />{$SNMP_SECNAME}  security name  ( snmpv3 Username ) <br />{$SNMP_AUTH}     authentication password.<br />{$SNMP_PRIV}     private password.</p>\n<p>iinclude this data :</p>\n<p>Admin status of interface <br />Operational status of interface<br />Description of interface<br />incomming traffic <br />Outgoing traffic</p>\n<p> </p>",
    "features": "Low Level Discovery (LLD)|SNMP Agent",
    "address": "",
    "city": "",
    "state": "",
    "country": "",
    "postcode": "",
    "telephone": "",
    "fax": "",
    "email": "",
    "website": "",
    "price": 0,
    "link_hits": 2498,
    "link_votes": 1,
    "link_rating": 5,
    "link_featured": null,
    "link_created": "2021-03-08 12:12:16",
    "link_modified": "2021-03-08 12:35:11",
    "link_visited": null,
    "publish_up": "2021-03-08 12:12:16",
    "publish_down": "0000-00-00 00:00:00",
    "metakey": "",
    "metadesc": "",
    "1.8": "",
    "2.0": "",
    "2.2": "",
    "2.4": "",
    "3.0": "",
    "3.2": "",
    "3.4": "",
    "4.0": "",
    "4.2": "CiscoSwitchInterfaceSNMPv3.xml",
    "4.4": "",
    "5.0": "",
    "5.2": "",
    "tags": "Cisco, Interface Discovery, SNMPv3",
    "author": "Omid Hosseini",
    "user_id": 13122,
    "link_id": 2357,
    "cat_id": "123",
    "internal_notes": "",
    "lat": 0,
    "lng": 0,
    "zoom": ""
}