{
    "link_name": "3CX Services Linux",
    "type": "Template",
    "OS": "",
    "vendor": "Others",
    "minZabbVer": "4.4.x",
    "link_desc": "<p>Template for monitoring 3cx services running on linux, this template contains trigger and items to monitor services related to the 3cx system, the postgresql and nginx database service.</p>\n<p> </p>\n<p>Note: As of version 18, the tunnel has been incorporated into the media server and this item/trigger must be disabled or excluded.</p>",
    "features": "Zabbix Agent",
    "address": "",
    "city": "",
    "state": "",
    "country": "",
    "postcode": "",
    "telephone": "",
    "fax": "",
    "email": "",
    "website": "https://github.com/antonytayron/Templates_Zabbix/blob/master/Template%203CX%20Services.xml",
    "price": 0,
    "link_hits": 3464,
    "link_votes": null,
    "link_rating": 0,
    "link_featured": null,
    "link_created": "2020-05-13 07:16:35",
    "link_modified": "2021-06-02 16:32:26",
    "link_visited": 1074,
    "publish_up": "2020-05-13 07:16:35",
    "publish_down": "0000-00-00 00:00:00",
    "metakey": "",
    "metadesc": "",
    "1.8": "",
    "2.0": "",
    "2.2": "",
    "2.4": "",
    "3.0": "",
    "3.2": "",
    "3.4": "",
    "4.0": "",
    "4.2": "",
    "4.4": "Template 3CX Services.xml",
    "5.0": "",
    "5.2": "",
    "tags": "",
    "author": "Antony T. N. Peronio",
    "user_id": 5976,
    "link_id": 2079,
    "cat_id": "194",
    "internal_notes": "",
    "lat": 0,
    "lng": 0,
    "zoom": ""
}