{
    "link_name": "Nakivo Backup & Replication",
    "type": "Template",
    "OS": "",
    "vendor": "Others",
    "minZabbVer": "4.0.x",
    "link_desc": "<p>External Zabbix Script with discovery rule for nakivo backups</p>",
    "features": "Low Level Discovery (LLD)|Zabbix Agent|Custom Script",
    "address": "",
    "city": "",
    "state": "",
    "country": "",
    "postcode": "",
    "telephone": "",
    "fax": "",
    "email": "",
    "website": "https://github.com/chises/zabbix-nakivo",
    "price": 0,
    "link_hits": 2165,
    "link_votes": null,
    "link_rating": 0,
    "link_featured": null,
    "link_created": "2019-06-11 12:30:39",
    "link_modified": "0000-00-00 00:00:00",
    "link_visited": 683,
    "publish_up": "2019-06-11 12:30:39",
    "publish_down": "0000-00-00 00:00:00",
    "metakey": "",
    "metadesc": "",
    "1.8": "",
    "2.0": "",
    "2.2": "",
    "2.4": "",
    "3.0": "",
    "3.2": "",
    "3.4": "",
    "4.0": "zbx_export_templates_nakivo.xml",
    "4.2": "",
    "4.4": "",
    "5.0": "",
    "5.2": "",
    "tags": "",
    "author": "Michael Weber",
    "user_id": 451,
    "link_id": 1672,
    "cat_id": "135",
    "internal_notes": "",
    "lat": 0,
    "lng": 0,
    "zoom": ""
}