{"link_name": "Template SNMP A10", "type": "Template", "OS": "", "vendor": "Others", "minZabbVer": "2.4.x", "link_desc": "<p>A10\u4ea4\u6362\u673a\u6a21\u677f</p>\n<p>\u5236\u4f5c\u7684\u65f6\u5019\u6ca1\u8003\u8651\u5230\u56fd\u9645\u5316\uff0c\u53ea\u80fd\u7ed9\u4e2d\u6587\u7528\u6237\u4f7f\u7528\u4e86</p>\n<p>\u90e8\u5206\u7ffb\u8bd1\u53ef\u80fd\u6709\u8bef\uff0c\u6b22\u8fce\u63d0\u4ea4pr\u7ed9\u6211</p>\n<p><strong>\u6ce8\u610f\uff1a\u5236\u4f5c\u7684\u65f6\u5019\u4f7f\u7528\u5230\u4e86valuemaps\uff0c\u8bf7\u5230\u4e0b\u9762\u7684\u94fe\u63a5\u5904\u4e0b\u8f7dvaluemaps.sql\u8ddfmappings.sql\u5bfc\u5165\u3002</strong></p>\n<p>github\uff1a<a href=\"https://github.com/0312birdzhang/Template-SNMP-A10\">https://github.com/0312birdzhang/Template-SNMP-A10</a></p>\n<p> </p>", "features": "SNMP Agent", "address": "", "city": "", "state": "", "country": "", "postcode": "", "telephone": "", "fax": "", "email": "", "website": "https://github.com/0312birdzhang/Template-SNMP-A10", "price": 0, "link_hits": 6265, "link_votes": 1, "link_rating": 5, "link_featured": null, "link_created": "2016-02-18 02:10:37", "link_modified": "2016-04-07 02:09:18", "link_visited": 776, "publish_up": "2016-02-18 02:10:37", "publish_down": "0000-00-00 00:00:00", "metakey": "", "metadesc": "", "1.8": "", "2.0": "", "2.2": "", "2.4": "Template-SNMP-A10.zip", "3.0": "", "3.2": "", "3.4": "", "4.0": "", "4.2": "", "4.4": "", "5.0": "", "5.2": "", "tags": "SNMP, A10", "author": "0312birdzhang", "user_id": 135, "link_id": 435, "cat_id": "236", "internal_notes": "", "lat": 0, "lng": 0, "zoom": ""}