{"link_name": "OpenVPN Server Traffic", "type": "Template", "OS": "", "vendor": "Zabbix", "minZabbVer": "2.2.x", "link_desc": "<h1>This is a zabbix-openvpn fork</h1>\n<p>Tested on Zabbix 4.4.1</p>\n<p>Main changes :</p>\n<ol>\n<li>Change so that the discovery is through the file openvpn-status.log</li>\n<li>Change to show data in bits instead of bytes</li>\n</ol>\n<p>Script for OpenVPN users monitoring. It shows an OpenVPN user\u2019s status, and its uplink and downlink traffic.</p>\n<p>Setup:</p>\n<ol>\n<li>\n<p>Copy the file discover_vpn.sh to any directory on the server were OpenVPN is(for example /etc/zabbix/scripts/discover_vpn.sh ). In this file specify the path to directory status log file.</p>\n</li>\n<li>\n<p>Copy all lines from \u201czabbix_agentd.txt\u201d file and paste to the end of zabbix agent config (/etc/zabbix/zabbix_agentd.conf). Check path to discover_vpn.sh.</p>\n</li>\n<li>\n<p>Import openvpn.xml to zabbix template.</p>\n</li>\n</ol>", "features": "Zabbix Agent", "address": "", "city": "", "state": "", "country": "", "postcode": "", "telephone": "", "fax": "", "email": "", "website": "https://github.com/filipenanclarez/zabbix-openvpn", "price": 0, "link_hits": 3239, "link_votes": null, "link_rating": 0, "link_featured": null, "link_created": "2020-04-19 21:17:25", "link_modified": "0000-00-00 00:00:00", "link_visited": 1118, "publish_up": "2020-04-19 21:17:25", "publish_down": "0000-00-00 00:00:00", "metakey": "", "metadesc": "", "1.8": "", "2.0": "", "2.2": "", "2.4": "", "3.0": "", "3.2": "", "3.4": "", "4.0": "", "4.2": "", "4.4": "", "5.0": "", "5.2": "", "tags": "openvpn", "author": "Filipe", "user_id": 11684, "link_id": 2061, "cat_id": "115", "internal_notes": "", "lat": 0, "lng": 0, "zoom": ""}