{"link_name": "\u30e4\u30de\u30cf \u30a4\u30f3\u30c6\u30ea\u30b8\u30a7\u30f3\u30c8L2\u30b9\u30a4\u30c3\u30c1\u30cf\u30d6 SWX2300", "type": "Template", "OS": "", "vendor": "Others", "minZabbVer": "2.2.x", "link_desc": "<p><span lang=\"en\"><span lang=\"en\">\u65e5\u672c\u88fd\u306e\u30e4\u30de\u30cf \u30a4\u30f3\u30c6\u30ea\u30b8\u30a7\u30f3\u30c8L2\u30b9\u30a4\u30c3\u30c1\u30f3\u30b0\u30cf\u30d6 SWX2300\u30b7\u30ea\u30fc\u30ba\u306e\u30c6\u30f3\u30d7\u30ec\u30fc\u30c8\u3092\u7f6e\u3044\u3066\u304a\u304d\u307e\u3059\u3002</span></span></p>\n<p><span lang=\"en\">CPU\u30fb\u30e1\u30e2\u30ea\u30fc\u306e\u4f7f\u7528\u7387\u3001\u30b7\u30b9\u30c6\u30e0\u306e\u518d\u8d77\u52d5\u306e\u56de\u6570\u3001\u30d5\u30a1\u30fc\u30e0\u30a6\u30a7\u30a2\u306eVer\u304c\u53d6\u5f97\u3067\u304d\u308b\u3088\u3046\u3057\u305f\u4e0a\u3067</span></p>\n<p><span lang=\"en\">LLD\u3067\u5404\u30dd\u30fc\u30c8\u306e\u72b6\u6cc1\u304c\u5224\u308b\u69d8\u306b\u3057\u307e\u3057\u305f\u3002</span></p>\n<p> \uff1c\u30a2\u30c3\u30d7\u30c7\u30fc\u30c8 \uff1e</p>\n<p>Ver2.2\u306e\u5834\u5408\u3067\u3082\u30a4\u30f3\u30dd\u30fc\u30c8\u304c\u51fa\u6765\u308b\u69d8\u306b\u306a\u308a\u307e\u3057\u305f\u306e\u3067\u65b0\u3057\u3044\u7269\u3068\u5dee\u3057\u66ff\u3048\u307e\u3059\u3002</p>\n<p>\u691c\u8a3c\u306e\u304a\u624b\u4f1d\u3044\u3092\u3057\u3066\u3044\u305f\u3060\u3044\u305f\u3001\u3068\u3063\u3068\u3053\u6c0f <a class=\"account-group js-account-group js-action-profile js-user-profile-link js-nav\" href=\"https://twitter.com/tottoko83746844\" data-user-id=\"741592407968382977\"><span class=\"username u-dir u-textTruncate\" dir=\"ltr\" data-aria-label-part=\"\"><span style=\"text-decoration: underline;\"><span style=\"color: #0066cc;\">@<b>tottoko83746844</b></span></span></span></a> \u306b\u611f\u8b1d\u3057\u307e\u3059\u3002</p>\n<p> </p>\n<p> </p>", "features": "Low Level Discovery (LLD)", "address": "", "city": "", "state": "", "country": "", "postcode": "", "telephone": "", "fax": "", "email": "", "website": "", "price": 0, "link_hits": 7528, "link_votes": null, "link_rating": 0, "link_featured": null, "link_created": "2018-04-04 06:10:21", "link_modified": "2018-04-27 06:00:09", "link_visited": null, "publish_up": "2018-04-04 06:10:21", "publish_down": "0000-00-00 00:00:00", "metakey": "", "metadesc": "", "1.8": "", "2.0": "", "2.2": "zbx_export_templates.xml", "2.4": "", "3.0": "", "3.2": "", "3.4": "", "4.0": "", "4.2": "", "4.4": "", "5.0": "", "5.2": "", "tags": "Japanese", "author": "Toshihiro_SKK", "user_id": 1371, "link_id": 1159, "cat_id": "348", "internal_notes": "", "lat": 0, "lng": 0, "zoom": ""}