{"link_name": "Zabbix Google Maps (GeoMaps) frontend integration", "type": "Integration", "OS": "General", "vendor": "Others", "minZabbVer": "4.4.x", "link_desc": "<h1><strong><span style=\"font-size: 12.16px;\">Check out the link for more information</span></strong></h1>\n<p>Recently we here at Opensource ICT Solutions have built a new integration for your Zabbix setup. A lot of Zabbix users have hosts that they want to display on the map. For example if you have Zabbix hosts that change location every few days or just to create an overview of your current Zabbix hosts.</p>\n<p> </p>\n<p>With our new integration we made this easy for you. We use Google Maps to display the Zabbix hosts right into your Zabbix frontend as you can check out the added image.</p>\n<p>There's a lot more to discover with this integration, so check out the link for more information.</p>", "features": "Zabbix Agent", "address": "", "city": "", "state": "", "country": "", "postcode": "", "telephone": "", "fax": "", "email": "", "website": "https://oicts.com/blog/2021/03/11/zabbix-google-maps-geomaps-frontend-integration/", "price": 0, "link_hits": 2258, "link_votes": 3, "link_rating": 5, "link_featured": null, "link_created": "2021-03-11 08:44:18", "link_modified": "2021-03-11 08:48:29", "link_visited": 1062, "publish_up": "2021-03-11 08:44:18", "publish_down": "0000-00-00 00:00:00", "metakey": "", "metadesc": "", "1.8": "", "2.0": "", "2.2": "", "2.4": "", "3.0": "", "3.2": "", "3.4": "", "4.0": "", "4.2": "", "4.4": "", "5.0": "", "5.2": "", "tags": "frontend, google maps, integration", "author": "Opensource ICT Solutions", "user_id": 10804, "link_id": 2366, "cat_id": "395", "internal_notes": "", "lat": 0, "lng": 0, "zoom": ""}