{
    "link_name": "Zabbix Slack AlertScript",
    "type": "Alert Script",
    "OS": "General",
    "vendor": "Zabbix",
    "minZabbVer": "1.8.x",
    "link_desc": "<h1 style=\"color: #000000; overflow-wrap: break-word; white-space: pre-wrap;\">Zabbix Slack AlertScript</h1>\n<h1 style=\"color: #000000; overflow-wrap: break-word; white-space: pre-wrap;\"> </h1>\n<h2 style=\"color: #000000; overflow-wrap: break-word; white-space: pre-wrap;\"><strong>About </strong></h2>\n<p style=\"color: #000000; overflow-wrap: break-word; white-space: pre-wrap;\">This is simply a Bash script that uses the custom alert script functionality within <a title=\"Zabbix\" href=\"https://www.zabbix.com/\" target=\"_blank\">Zabbix</a> along with the incoming web-hook feature of <a title=\"Slack\" href=\"https://slack.com/\" target=\"_blank\">Slack</a>.</p>\n<h2 style=\"color: #000000; overflow-wrap: break-word; white-space: pre-wrap;\"><strong>Versions</strong></h2>\n<p style=\"color: #000000; overflow-wrap: break-word; white-space: pre-wrap;\">This works with Zabbix 1.8 or greater - including 2.x and 3.x, as well as the newest 4.0 and 4.2 versions!</p>\n<h2 style=\"color: #000000; overflow-wrap: break-word; white-space: pre-wrap;\"><strong>Installation</strong></h2>\n<p style=\"color: #000000; overflow-wrap: break-word; white-space: pre-wrap;\">Additional information including installation and configuration instructions can be found on <a title=\"zabbix-slack-alertscript GitHub repository\" href=\"https://github.com/ericoc/zabbix-slack-alertscript\" target=\"_blank\">the official GitHub repository</a>.</p>",
    "features": "Custom Script",
    "address": "",
    "city": "",
    "state": "",
    "country": "",
    "postcode": "",
    "telephone": "",
    "fax": "",
    "email": "",
    "website": "https://github.com/ericoc/zabbix-slack-alertscript",
    "price": 0,
    "link_hits": 9555,
    "link_votes": null,
    "link_rating": 0,
    "link_featured": null,
    "link_created": "2019-04-11 17:53:58",
    "link_modified": "2019-04-11 18:06:47",
    "link_visited": 327,
    "publish_up": "2019-04-11 17:53:58",
    "publish_down": "0000-00-00 00:00:00",
    "metakey": "",
    "metadesc": "",
    "1.8": "slack.sh.zip",
    "2.0": "slack.sh.zip",
    "2.2": "slack.sh.zip",
    "2.4": "slack.sh.zip",
    "3.0": "slack.sh.zip",
    "3.2": "slack.sh.zip",
    "3.4": "slack.sh.zip",
    "4.0": "slack.sh.zip",
    "4.2": "",
    "4.4": "",
    "5.0": "",
    "5.2": "",
    "tags": "slack, zabbix, alertscript, github, bash, shell",
    "author": "Eric O'Callaghan",
    "user_id": 9639,
    "link_id": 1600,
    "cat_id": "395",
    "internal_notes": "",
    "lat": 0,
    "lng": 0,
    "zoom": ""
}