{"link_name": "(Template) Windows Iperius Backup", "type": "Template", "OS": "Microsoft Windows", "vendor": "", "minZabbVer": "3.2.x", "link_desc": "<p>Desenvolvido por Diego Cavalcante - 22/12/2017<br /> E-Mail: <a href=\"mailto:diego@suportecavalcante.com.br\">diego@suportecavalcante.com.br</a><br /><span style=\"font-size: 12.16px;\">Telegram</span><span style=\"font-size: 12.16px;\">: </span><span style=\"font-size: 12.16px;\">@diego_cavalcante </span><br /> Descri\u00e7\u00e3o: Monitora atividade de Jobs do Iperius Backup<br /> S.O: Windows<br /> Linguagem: Powershell + UserParameter<br /> Tipo: Low Level Discovery</p>\n<p>Caso voc\u00ea tenha instalado o software Iperius Backup em seu servidor, e deseja coletar o status e outros dados importantes dos Jobs configurados, siga os passos abaixo. Com um pouco de Powershell e leitura de Logs \u00e9 s\u00f3 o que precisamos para monitor\u00e1-lo, o software tem sua vers\u00e3o free (com algumas limita\u00e7\u00f5es) e a vers\u00e3o paga, e em ambos os casos o monitoramento pode ser realizado.</p>\n<h4>\u00b0 ITENS</h4>\n<p>\u00b0 LLD Status {#JOBCONF}<br /> \u00b0 LLD Nome {#JOBCONF}<br /> \u00b0 LLD Inicio do Job {#JOBCONF}<br /> \u00b0 LLD Fim do Job {#JOBCONF}<br /> \u00b0 LLD Tempo Decorrido do Job {#JOBCONF}<br /> \u00b0 Servi\u00e7o Iperius Backup</p>\n<h4>\u00b0 TRIGGERS</h4>\n<p>\u00b0 LLD Status do Job {#JOBCONF}</p>\n<h4>\u00b0 GR\u00c1FICOS</h4>\n<p>\u00b0 LLD Status do Job {#JOBCONF}</p>", "features": "Low Level Discovery (LLD)|Zabbix Agent Active", "address": "", "city": "", "state": "", "country": "", "postcode": "", "telephone": "", "fax": "", "email": "", "website": "https://github.com/suportecavalcante", "price": 0, "link_hits": 38284, "link_votes": 1, "link_rating": 5, "link_featured": null, "link_created": "2018-01-06 18:59:57", "link_modified": "2018-07-07 13:31:10", "link_visited": 623, "publish_up": "2018-01-06 18:59:57", "publish_down": "0000-00-00 00:00:00", "metakey": "", "metadesc": "", "1.8": "", "2.0": "", "2.2": "", "2.4": "", "3.0": "", "3.2": "zabbix.backup.iperius.zip", "3.4": "", "4.0": "", "4.2": "", "4.4": "", "5.0": "", "5.2": "", "tags": "microsoft, windows, lld, iperius, backup", "author": "Diego Cavalcante", "user_id": 4554, "link_id": 1045, "cat_id": "180", "internal_notes": "", "lat": 0, "lng": 0, "zoom": ""}