{
    "link_name": "Windows Physical drive IOPS",
    "type": "Template",
    "OS": "Microsoft Windows",
    "vendor": "",
    "minZabbVer": "3.4.x",
    "link_desc": "<p>This template discover physical disk thrue a powershell code.</p>\n<p>As i hate myself to deploy third party scripts on my agents, the powershell code is embeded in this template macro, this mean that you don't have to deploy any additionnal scripts to get it work.</p>\n<p>It also use \"zabbix active\" items to get work behind firewall.</p>\n<p>Data are retrieved thrue perfmon values, the template has been made to be compatible with all OS language using numeric value of perfcounter.</p>\n<p>This template is better than others because this one calculate the IOPS per physical disk instead of logical drive, meaning a better estimation of true saturation of a disk.</p>\n<p>If trigger fire on physical disk too much, it's time to buy SSD :)</p>\n<p>Look at the attached screenshots to get a better idea of it.</p>\n<p> </p>\n<p>Enjoy</p>\n<p>PS: powershell macro has been base64 encoded to be more easy to deploy, if you do not trust the code you can easily revert it back to something readable or just look at the Zabbix Agent log to see the command executed</p>\n<p>Tested from Windows 7 till 2016 with success.</p>",
    "features": "Zabbix Agent Active",
    "address": "",
    "city": "",
    "state": "",
    "country": "",
    "postcode": "",
    "telephone": "",
    "fax": "",
    "email": "",
    "website": "",
    "price": 0,
    "link_hits": 18420,
    "link_votes": null,
    "link_rating": 0,
    "link_featured": null,
    "link_created": "2018-07-09 13:43:32",
    "link_modified": "2018-07-09 13:47:33",
    "link_visited": null,
    "publish_up": "2018-07-09 13:43:32",
    "publish_down": "0000-00-00 00:00:00",
    "metakey": "",
    "metadesc": "",
    "1.8": "",
    "2.0": "",
    "2.2": "",
    "2.4": "",
    "3.0": "",
    "3.2": "",
    "3.4": "Windows_Physical_Disk_IOPS_templates.xml",
    "4.0": "",
    "4.2": "",
    "4.4": "",
    "5.0": "",
    "5.2": "",
    "tags": "Windows, IOPS, queue, latency, physical, disk",
    "author": "C\u00e9dric MARCOUX",
    "user_id": 6195,
    "link_id": 1246,
    "cat_id": "180",
    "internal_notes": "",
    "lat": 0,
    "lng": 0,
    "zoom": ""
}