{
    "link_name": "Jira monitoring",
    "type": "Template",
    "OS": "",
    "vendor": "Others",
    "minZabbVer": "2.2.x",
    "link_desc": "<p>Zabbix template and config file for monitoring Jira - issue tracking software developed by Atlassian.<br />Passive and active checks. Provides monitoring statistics from jira mysql database.<br /><br />Installation:<br /><br />  1. Import template in Zabbix Web ui<br />  2. Add jira.conf file to Zabbix Agent includes dir (or add UserParameters lines to agent config file)<br />  3. In jira.conf, replace SECRETPASSWORD with your jira mysql database password<br />  4. Connect proper template to host (for active or passive checks)<br />  5. Restart agent<br />  <br />  Tested on Zabbix 2.4</p>",
    "features": "Zabbix Agent|Zabbix Agent Active",
    "address": "",
    "city": "",
    "state": "",
    "country": "",
    "postcode": "",
    "telephone": "",
    "fax": "",
    "email": "",
    "website": "",
    "price": 0,
    "link_hits": 12937,
    "link_votes": null,
    "link_rating": 0,
    "link_featured": null,
    "link_created": "2017-07-19 12:20:45",
    "link_modified": "0000-00-00 00:00:00",
    "link_visited": null,
    "publish_up": "2017-07-19 12:20:45",
    "publish_down": "0000-00-00 00:00:00",
    "metakey": "",
    "metadesc": "",
    "1.8": "",
    "2.0": "",
    "2.2": "",
    "2.4": "Jira_zabbix.zip",
    "3.0": "",
    "3.2": "",
    "3.4": "",
    "4.0": "",
    "4.2": "",
    "4.4": "",
    "5.0": "",
    "5.2": "",
    "tags": "jira, atlassian",
    "author": "Mikolaj Porczynski",
    "user_id": 1198,
    "link_id": 885,
    "cat_id": "324",
    "internal_notes": "",
    "lat": 0,
    "lng": 0,
    "zoom": ""
}