{"link_name": "Restic backup", "type": "Template", "OS": "", "vendor": "Others", "minZabbVer": "4.4.x", "link_desc": "<div>Get alerts when your restic backup have failed, or didn't finish on time. The default is in last 26 hours but can be changed via a MACRO.</div>\n<div> </div>\n<div>Two MACROs are available:</div>\n<ul>\n<li><code>{$BACKUP_STATUS_FILE}</code> which contain the full path of the status file. Default is <code>/home/backup/status.json</code>.</li>\n<li><code>{$MAX_HOURS_BETWEEN}</code> which contain the maximum number of hours before it triggers an alert. Default is `26` hours (for backup running once a day, plus some time if it takes a bit longer than usual).</li>\n</ul>\n<div> This is using the status file generated by <a href=\"https://github.com/creativeprojects/resticprofile/\">resticprofile</a>.</div>\n<div> </div>\n<div>For more information, see the <a href=\"https://github.com/creativeprojects/resticprofile/tree/master/contrib/zabbix\">README</a>.</div>", "features": "Zabbix Agent|Zabbix Agent Active", "address": "", "city": "", "state": "", "country": "", "postcode": "", "telephone": "", "fax": "", "email": "", "website": "https://github.com/creativeprojects/resticprofile/tree/master/contrib/zabbix", "price": 0, "link_hits": 450, "link_votes": null, "link_rating": 0, "link_featured": null, "link_created": "2021-02-21 19:25:15", "link_modified": "2021-02-21 19:47:29", "link_visited": 155, "publish_up": "2021-02-21 19:25:15", "publish_down": "0000-00-00 00:00:00", "metakey": "", "metadesc": "", "1.8": "", "2.0": "", "2.2": "", "2.4": "", "3.0": "", "3.2": "", "3.4": "", "4.0": "", "4.2": "", "4.4": "", "5.0": "zbx_resticprofile_templates.xml", "5.2": "", "tags": "restic, resticprofile, backup", "author": "", "user_id": 13051, "link_id": 2339, "cat_id": "135", "internal_notes": "", "lat": 0, "lng": 0, "zoom": ""}