{"link_name": "Zabbix template for LLD SNMPv3 Cisco network devices (switches and routers) with authentication and AES/DES encryption.", "type": "Template", "OS": "General", "vendor": "Cisco", "minZabbVer": "3.4.x", "link_desc": "<p>Zabbix template for LLD SNMPv3 Cisco network devices (switches and routers) with authentication and AES/DES encryption.<br /><br />Template use next macros:<br /><br /><strong>{$SNMP_V3_CONTEXTNAME}</strong> - context name.<br /><strong>{$SNMP_V3_SECURITYNAME}</strong> - security name.<br /><strong>{$SNMP_V3_AUTHPASSPHRASE}</strong> - authentication password.<br /><strong>{$SNMP_V3_PRIVPASSPHRASE}</strong> - private password.<br /><br />Template has two version: for AES and DES encryption. There is localization Russian version for both too. <br /><br />Template use SHA authentication method. SNMP port is default.<br /><br />Template tested in Zabbix 3.4 and 4.0. <br /><br />It work with next Cisco switches on AES encryption:<br />- 2960<br />- 2960G<br />- 2960X<br />- 3550<br />- 3750G<br /><br />It work with next Cisco switches on DES encryption:<br />- 2950<br />- 2950G<br /><br />It work with next Cisco routers on AES encryption:<br />- 2811<br /><br />Template content:<br /><em>- 4 element items:</em><br /> * temperature<br /> * CPU average load (5 min)<br /> * free memory<br /> * and some data from extrenal check by BASH-script:<br />  - IOS version<br />  - IOS flash file name<br />  - uptime<br />  - cooler status<br />  - temperature status<br />  - description of interface<br />  - admin status of interface<br />  - operational status of interface<br />  - VLAN/trunk of interface<br />   <br /><em>- 3 triggers:</em><br /> * CPU high load of network item<br /> * Memory high load of network item<br /> * Temperature very high of network item<br /> <br /><em>- 1 graphic:</em><br /> * CPU and memory average load<br /> <br /><em>- 1 discovery rule for:</em><br />  8 element items prototypes<br />  -- Admin status of interface<br />  -- Alias of interface<br />  -- Description of interface<br />  -- Inbound errors on interface<br />  -- Incoming traffic on interafce<br />  -- Operational status of interface<br />  -- Outbound errors on interface<br />  -- Outgoing traffic on interface<br />  <br /> <em> 2 triggers prototypes</em><br />  -- Inbound errors host on interface<br />  -- Outbound errors host on interface<br />  <br /> <em> 1 graphic prototype:</em><br />  -- Traffic of interface</p>", "features": "SNMP Agent", "address": "", "city": "", "state": "", "country": "", "postcode": "", "telephone": "", "fax": "", "email": "", "website": "https://github.com/igor-a-silkin/Zabbix-SNMPv3-Template", "price": 0, "link_hits": 9869, "link_votes": null, "link_rating": 0, "link_featured": null, "link_created": "2019-02-07 06:45:00", "link_modified": "2019-02-07 08:28:00", "link_visited": 3025, "publish_up": "2019-02-07 06:45:00", "publish_down": "0000-00-00 00:00:00", "metakey": "", "metadesc": "", "1.8": "", "2.0": "", "2.2": "", "2.4": "", "3.0": "", "3.2": "", "3.4": "", "4.0": "", "4.2": "", "4.4": "", "5.0": "", "5.2": "", "tags": "", "author": "Silkin Igor", "user_id": 9143, "link_id": 1543, "cat_id": "395", "internal_notes": "", "lat": 0, "lng": 0, "zoom": ""}