{
    "link_name": "Synology DSM 5+ (Updated)",
    "type": "Template",
    "OS": "",
    "vendor": "Synology",
    "minZabbVer": "3.2.x",
    "link_desc": "<p>Cleaned Up template that is originally from <a href=\"storage-devices/synology/synology-dsm-5\">https://share.zabbix.com/storage-devices/synology/synology-dsm-5</a></p>\n<p>Added</p>\n<p>-CPU load average</p>\n<p>-Template for each CPU discovery</p>\n<p>-Template for Interface discovery</p>\n<p>-Trigger for Updates</p>\n<p>-Template for Disk Discovery</p>",
    "features": "Low Level Discovery (LLD)|SNMP Agent",
    "address": "",
    "city": "",
    "state": "",
    "country": "",
    "postcode": "",
    "telephone": "",
    "fax": "",
    "email": "",
    "website": "https://github.com/samwiseg00/zabbix",
    "price": 0,
    "link_hits": 23835,
    "link_votes": null,
    "link_rating": 0,
    "link_featured": null,
    "link_created": "2017-05-17 22:57:38",
    "link_modified": "2018-02-13 20:00:46",
    "link_visited": 3575,
    "publish_up": "2017-05-17 22:57:38",
    "publish_down": "0000-00-00 00:00:00",
    "metakey": "",
    "metadesc": "",
    "1.8": "",
    "2.0": "",
    "2.2": "",
    "2.4": "",
    "3.0": "",
    "3.2": "Template Synology 6.xml",
    "3.4": "",
    "4.0": "",
    "4.2": "",
    "4.4": "",
    "5.0": "",
    "5.2": "",
    "tags": "synology, nas, disk",
    "author": "samwaiseg0",
    "user_id": 2345,
    "link_id": 832,
    "cat_id": "175",
    "internal_notes": "",
    "lat": 0,
    "lng": 0,
    "zoom": ""
}