{
    "link_name": "NextCloud v. 14 Monitoring",
    "type": "Template",
    "OS": "",
    "vendor": "Others",
    "minZabbVer": "4.0.x",
    "link_desc": "<ul>\n<li style=\"margin-bottom: 0in; line-height: 100%;\"><strong>Note that this is a version 0.1 of the template. The included script is very quick and dirty.</strong></li>\n<li style=\"margin-bottom: 0in; line-height: 100%;\"><strong>Note that this template was tested against NextCloud version 14.0.</strong></li>\n<li style=\"margin-bottom: 0in; line-height: 100%;\"><strong>Note that this template was created and testes under the 4.0.2 version of Zabbix.</strong></li>\n<li style=\"margin-bottom: 0in; line-height: 100%;\"><strong>Note that this template is non-official and not being maintained by Zabbix SIA or NextCloud GmbH.</strong></li>\n</ul>\n<p style=\"margin-bottom: 0in; line-height: 100%;\">The template utilizes the HTTP Agent, Master\\Dependent items, Shell script, and NextCloud\u2019s REST API and Preprocessing steps</p>\n<p style=\"margin-bottom: 0in; line-height: 100%;\"><a href=\"https://www.zabbix.com/documentation/4.0/manual/config/items/itemtypes/external\" target=\"_blank\">The script must be placed in the ExternalScripts directory, be executable and runnable by </a>zabbix<a href=\"https://www.zabbix.com/documentation/4.0/manual/config/items/itemtypes/external\" target=\"_blank\"> user.</a></p>\n<p style=\"margin-bottom: 0in; line-height: 100%;\"><strong>You must configure at least the following macro:</strong></p>\n<ul>\n<li style=\"margin-bottom: 0in; line-height: 100%;\">{$T_NEXTCLOUD_USER} \u2013 your admin username</li>\n<li style=\"margin-bottom: 0in; line-height: 100%;\">{$T_NEXTCLOUD_PASSWORD}- your admin password</li>\n<li style=\"margin-bottom: 0in; line-height: 100%;\">{$T_NEXTCLOUD_PATH}- path to the nextcloud, i.e. /nextcloud.  </li>\n</ul>\n<h4 style=\"margin-bottom: 0in; line-height: 100%;\">Standard metrics:</h4>\n<ul>\n<li style=\"margin-bottom: 0in; line-height: 100%;\"><strong>General</strong>\n<ul>\n<li>NextCloud version</li>\n<li>Web server engine and version</li>\n<li>DB type</li>\n<li>DB size</li>\n</ul>\n</li>\n<li style=\"margin-bottom: 0in; line-height: 100%;\"><strong>Security</strong>\n<ul>\n<li style=\"margin-bottom: 0in; line-height: 100%;\">Password must contain numerical characters</li>\n<li style=\"margin-bottom: 0in; line-height: 100%;\">Password must be a mix of Upper/Lower case characters</li>\n<li style=\"margin-bottom: 0in; line-height: 100%;\">Password must contain special characters</li>\n<li style=\"margin-bottom: 0in; line-height: 100%;\">Minimum password length</li>\n<li style=\"margin-bottom: 0in; line-height: 100%;\">Number of shared links w/o password protection</li>\n</ul>\n</li>\n</ul>\n<ul>\n<li style=\"margin-bottom: 0in; line-height: 100%;\"><strong>Users</strong>\n<ul>\n<li style=\"margin-bottom: 0in; line-height: 100%;\">Number of active users for past 24h</li>\n<li style=\"margin-bottom: 0in; line-height: 100%;\">Number of registered users</li>\n</ul>\n</li>\n</ul>\n<p style=\"margin-bottom: 0in; line-height: 100%;\"><strong>+ LLD Discovered items</strong></p>",
    "features": "Low Level Discovery (LLD)|Custom Script|Dependent Items|HTTP Agent",
    "address": "",
    "city": "",
    "state": "",
    "country": "",
    "postcode": "",
    "telephone": "",
    "fax": "",
    "email": "",
    "website": "",
    "price": 0,
    "link_hits": 3464,
    "link_votes": null,
    "link_rating": 0,
    "link_featured": null,
    "link_created": "2018-12-24 14:42:26",
    "link_modified": "2018-12-24 14:51:59",
    "link_visited": null,
    "publish_up": "2018-12-24 14:42:26",
    "publish_down": "0000-00-00 00:00:00",
    "metakey": "",
    "metadesc": "",
    "1.8": "",
    "2.0": "",
    "2.2": "",
    "2.4": "",
    "3.0": "",
    "3.2": "",
    "3.4": "",
    "4.0": "nextcloud_v01_zabbix.zip",
    "4.2": "",
    "4.4": "",
    "5.0": "",
    "5.2": "",
    "tags": "nextcloud, file share, api, http agent",
    "author": "Aleksejs Petrovs",
    "user_id": 8819,
    "link_id": 1479,
    "cat_id": "115",
    "internal_notes": "",
    "lat": 0,
    "lng": 0,
    "zoom": ""
}