{"link_name": "QUIDO Papouch", "type": "Template", "OS": "General", "vendor": "Generic", "minZabbVer": "4.4.x", "link_desc": "<p>Autodiscovery of inputs a outputs, Temperature senzor + graph, triggers</p>\n<p><a>https://papouch.com/io-moduly/</a></p>\n<p><span class=\"VIiyi\" lang=\"en\"><span class=\"JLqJ4b ChMk0b\" data-language-for-alternatives=\"en\" data-language-to-translate-into=\"auto\" data-phrase-index=\"0\"><a href=\"mailto:priechodsky.dusan@gmail.com\">Send me</a> what template you need, or if this template helped you, <a href=\"https://ko-fi.com/priechodskydusan\">you can buy me one coffee</a> :)</span></span></p>", "features": "SNMP Agent", "address": "", "city": "", "state": "", "country": "", "postcode": "", "telephone": "", "fax": "", "email": "", "website": "https://github.com/priechodsky/Quido-Papouch/blob/master/QUIDO%20Papouch.xml", "price": 0, "link_hits": 573, "link_votes": null, "link_rating": 0, "link_featured": null, "link_created": "2020-08-17 08:27:26", "link_modified": "2021-03-02 23:07:22", "link_visited": 155, "publish_up": "2020-08-17 08:27:26", "publish_down": "0000-00-00 00:00:00", "metakey": "", "metadesc": "", "1.8": "", "2.0": "", "2.2": "", "2.4": "", "3.0": "", "3.2": "", "3.4": "", "4.0": "", "4.2": "", "4.4": "", "5.0": "QUIDO Papouch.xml", "5.2": "", "tags": "", "author": "Dusan Priechodsky", "user_id": 12210, "link_id": 2167, "cat_id": "403", "internal_notes": "", "lat": 0, "lng": 0, "zoom": ""}