{
    "link_name": "Eaton Powerware 9150",
    "type": "Template",
    "OS": "",
    "vendor": "Others",
    "minZabbVer": "2.2.x",
    "link_desc": "<p>This template based on \"Eaton Powerware 9130\" by \u0410\u043b\u0435\u043a\u0441\u0435\u0439 \u041f\u0443\u0441\u0442\u043e\u0432\u0430\u043b\u043e\u0432.</p>\n<p>I add 2 triggers and make 2 fixes to make it compare with 9150.</p>\n<p>You may need some old items to add this template to older versions of zabbix. You can download it from oficial zabbix site.</p>",
    "features": "Zabbix Agent",
    "address": "",
    "city": "",
    "state": "",
    "country": "",
    "postcode": "",
    "telephone": "",
    "fax": "",
    "email": "",
    "website": "",
    "price": 0,
    "link_hits": 2053,
    "link_votes": null,
    "link_rating": 0,
    "link_featured": null,
    "link_created": "2018-03-05 11:00:34",
    "link_modified": "2018-03-05 11:11:07",
    "link_visited": null,
    "publish_up": "2018-03-05 11:00:34",
    "publish_down": "0000-00-00 00:00:00",
    "metakey": "",
    "metadesc": "",
    "1.8": "",
    "2.0": "Powerware_9150_template.xml",
    "2.2": "",
    "2.4": "",
    "3.0": "",
    "3.2": "",
    "3.4": "",
    "4.0": "",
    "4.2": "",
    "4.4": "",
    "5.0": "",
    "5.2": "",
    "tags": "",
    "author": "",
    "user_id": 5198,
    "link_id": 1122,
    "cat_id": "128",
    "internal_notes": "",
    "lat": 0,
    "lng": 0,
    "zoom": ""
}