{
    "link_name": "D-Link DGS 1100",
    "type": "Template",
    "OS": "",
    "vendor": "Zabbix",
    "minZabbVer": "5.0.x",
    "link_desc": "\t<p>Template for D'Link DGS 1100 SNMPv2, Includes discovery(items, graphs, triggers)</p>\n<div id=\"simple-translate\"> </div>",
    "features": "SNMP Agent",
    "address": "",
    "city": "",
    "state": "",
    "country": "",
    "postcode": "",
    "telephone": "",
    "fax": "",
    "email": "",
    "website": "https://github.com/Mayamee/D-Link-DGS-1100-Template-Zabbix",
    "price": 0,
    "link_hits": 54,
    "link_votes": null,
    "link_rating": 0,
    "link_featured": null,
    "link_created": "2021-08-10 11:28:14",
    "link_modified": "2021-08-16 09:35:22",
    "link_visited": 14,
    "publish_up": "2021-08-10 11:28:14",
    "publish_down": "0000-00-00 00:00:00",
    "metakey": "",
    "metadesc": "",
    "1.8": "",
    "2.0": "",
    "2.2": "",
    "2.4": "",
    "3.0": "",
    "3.2": "",
    "3.4": "",
    "4.0": "",
    "4.2": "",
    "4.4": "",
    "5.0": "D-Link DGS 1100.xml",
    "5.2": "",
    "tags": "",
    "author": "Mew",
    "user_id": 13737,
    "link_id": 2531,
    "cat_id": "122,112",
    "internal_notes": "",
    "lat": 0,
    "lng": 0,
    "zoom": ""
}