{
    "link_name": "Template Optical Modules Huawei",
    "type": "Template",
    "OS": "",
    "vendor": "Huawei",
    "minZabbVer": "4.2.x",
    "link_desc": "<p>Template with single lane discovery and multi lane devices.</p>\n<p><br />Cr\u00e9ditos \u00e0 https://github.com/GustavoIFelippe</p>",
    "features": "SNMP Agent",
    "address": "",
    "city": "",
    "state": "",
    "country": "",
    "postcode": "",
    "telephone": "",
    "fax": "",
    "email": "",
    "website": "https://github.com/carlosviatroski/zabbixtemplates/blob/main/Template%20Optical%20Modules%20Huawei.xml",
    "price": 0,
    "link_hits": 1730,
    "link_votes": null,
    "link_rating": 0,
    "link_featured": null,
    "link_created": "2020-12-07 12:13:27",
    "link_modified": "2020-12-11 13:55:13",
    "link_visited": 366,
    "publish_up": "2020-12-07 12:13:27",
    "publish_down": "0000-00-00 00:00:00",
    "metakey": "",
    "metadesc": "",
    "1.8": "",
    "2.0": "",
    "2.2": "",
    "2.4": "",
    "3.0": "",
    "3.2": "",
    "3.4": "",
    "4.0": "",
    "4.2": "Template Optical Modules Huawei.xml",
    "4.4": "Template Optical Modules Huawei.xml",
    "5.0": "Template Optical Modules Huawei.xml",
    "5.2": "",
    "tags": "optical, huawei, sfp, qsfp, signal, rx",
    "author": "gustavo10telecom",
    "user_id": 12752,
    "link_id": 2262,
    "cat_id": "317",
    "internal_notes": "",
    "lat": 0,
    "lng": 0,
    "zoom": ""
}